
{
	"sources" : 
	[
		
		{
			"file" : "E:/D/MITK/Plugins/org.blueberry.ui.qt/src/berryAbstractSourceProvider.cpp"
		},
		
		{
			"file" : "E:/D/MITK/Plugins/org.blueberry.ui.qt/src/berryAbstractUICTKPlugin.cpp"
		},
		
		{
			"file" : "E:/D/MITK/Plugins/org.blueberry.ui.qt/src/berryConstants.cpp"
		},
		
		{
			"file" : "E:/D/MITK/Plugins/org.blueberry.ui.qt/src/berryDisplay.cpp"
		},
		
		{
			"file" : "E:/D/MITK/Plugins/org.blueberry.ui.qt/src/berryEditorPart.cpp"
		},
		
		{
			"file" : "E:/D/MITK/Plugins/org.blueberry.ui.qt/src/berryExtensionFactory.cpp"
		},
		
		{
			"file" : "E:/D/MITK/Plugins/org.blueberry.ui.qt/src/berryFileEditorInput.cpp"
		},
		
		{
			"file" : "E:/D/MITK/Plugins/org.blueberry.ui.qt/src/berryGeometry.cpp"
		},
		
		{
			"file" : "E:/D/MITK/Plugins/org.blueberry.ui.qt/src/berryIActionBars.h"
		},
		
		{
			"file" : "E:/D/MITK/Plugins/org.blueberry.ui.qt/src/berryIContextService.cpp"
		},
		
		{
			"file" : "E:/D/MITK/Plugins/org.blueberry.ui.qt/src/berryIContributionRoot.h"
		},
		
		{
			"file" : "E:/D/MITK/Plugins/org.blueberry.ui.qt/src/berryIDropTargetListener.cpp"
		},
		
		{
			"file" : "E:/D/MITK/Plugins/org.blueberry.ui.qt/src/berryIEditorDescriptor.cpp"
		},
		
		{
			"file" : "E:/D/MITK/Plugins/org.blueberry.ui.qt/src/berryIEditorInput.cpp"
		},
		
		{
			"file" : "E:/D/MITK/Plugins/org.blueberry.ui.qt/src/berryIEditorMatchingStrategy.cpp"
		},
		
		{
			"file" : "E:/D/MITK/Plugins/org.blueberry.ui.qt/src/berryIEditorPart.cpp"
		},
		
		{
			"file" : "E:/D/MITK/Plugins/org.blueberry.ui.qt/src/berryIEditorReference.cpp"
		},
		
		{
			"file" : "E:/D/MITK/Plugins/org.blueberry.ui.qt/src/berryIEditorRegistry.cpp"
		},
		
		{
			"file" : "E:/D/MITK/Plugins/org.blueberry.ui.qt/src/berryIEditorSite.cpp"
		},
		
		{
			"file" : "E:/D/MITK/Plugins/org.blueberry.ui.qt/src/berryIElementFactory.cpp"
		},
		
		{
			"file" : "E:/D/MITK/Plugins/org.blueberry.ui.qt/src/berryIFileEditorMapping.cpp"
		},
		
		{
			"file" : "E:/D/MITK/Plugins/org.blueberry.ui.qt/src/berryIFolderLayout.cpp"
		},
		
		{
			"file" : "E:/D/MITK/Plugins/org.blueberry.ui.qt/src/berryIMemento.cpp"
		},
		
		{
			"file" : "E:/D/MITK/Plugins/org.blueberry.ui.qt/src/berryINullSelectionListener.cpp"
		},
		
		{
			"file" : "E:/D/MITK/Plugins/org.blueberry.ui.qt/src/berryIPageLayout.cpp"
		},
		
		{
			"file" : "E:/D/MITK/Plugins/org.blueberry.ui.qt/src/berryIPartListener.cpp"
		},
		
		{
			"file" : "E:/D/MITK/Plugins/org.blueberry.ui.qt/src/berryIPageService.cpp"
		},
		
		{
			"file" : "E:/D/MITK/Plugins/org.blueberry.ui.qt/src/berryIPartService.cpp"
		},
		
		{
			"file" : "E:/D/MITK/Plugins/org.blueberry.ui.qt/src/berryIPathEditorInput.cpp"
		},
		
		{
			"file" : "E:/D/MITK/Plugins/org.blueberry.ui.qt/src/berryIPersistable.cpp"
		},
		
		{
			"file" : "E:/D/MITK/Plugins/org.blueberry.ui.qt/src/berryIPersistableElement.h"
		},
		
		{
			"file" : "E:/D/MITK/Plugins/org.blueberry.ui.qt/src/berryIPerspectiveDescriptor.cpp"
		},
		
		{
			"file" : "E:/D/MITK/Plugins/org.blueberry.ui.qt/src/berryIPerspectiveFactory.cpp"
		},
		
		{
			"file" : "E:/D/MITK/Plugins/org.blueberry.ui.qt/src/berryIPerspectiveListener.cpp"
		},
		
		{
			"file" : "E:/D/MITK/Plugins/org.blueberry.ui.qt/src/berryIPerspectiveRegistry.cpp"
		},
		
		{
			"file" : "E:/D/MITK/Plugins/org.blueberry.ui.qt/src/berryIPlaceholderFolderLayout.cpp"
		},
		
		{
			"file" : "E:/D/MITK/Plugins/org.blueberry.ui.qt/src/berryIPluginContribution.h"
		},
		
		{
			"file" : "E:/D/MITK/Plugins/org.blueberry.ui.qt/src/berryIPostSelectionProvider.cpp"
		},
		
		{
			"file" : "E:/D/MITK/Plugins/org.blueberry.ui.qt/src/berryIPreferencePage.cpp"
		},
		
		{
			"file" : "E:/D/MITK/Plugins/org.blueberry.ui.qt/src/berryIPropertyChangeListener.cpp"
		},
		
		{
			"file" : "E:/D/MITK/Plugins/org.blueberry.ui.qt/src/berryIQtPreferencePage.cpp"
		},
		
		{
			"file" : "E:/D/MITK/Plugins/org.blueberry.ui.qt/src/berryIQtStyleManager.cpp"
		},
		
		{
			"file" : "E:/D/MITK/Plugins/org.blueberry.ui.qt/src/berryIReusableEditor.cpp"
		},
		
		{
			"file" : "E:/D/MITK/Plugins/org.blueberry.ui.qt/src/berryISaveablePart.cpp"
		},
		
		{
			"file" : "E:/D/MITK/Plugins/org.blueberry.ui.qt/src/berryISaveablesLifecycleListener.cpp"
		},
		
		{
			"file" : "E:/D/MITK/Plugins/org.blueberry.ui.qt/src/berryISaveablesSource.cpp"
		},
		
		{
			"file" : "E:/D/MITK/Plugins/org.blueberry.ui.qt/src/berryISelection.cpp"
		},
		
		{
			"file" : "E:/D/MITK/Plugins/org.blueberry.ui.qt/src/berryISelectionChangedListener.cpp"
		},
		
		{
			"file" : "E:/D/MITK/Plugins/org.blueberry.ui.qt/src/berryISelectionListener.cpp"
		},
		
		{
			"file" : "E:/D/MITK/Plugins/org.blueberry.ui.qt/src/berryISelectionProvider.cpp"
		},
		
		{
			"file" : "E:/D/MITK/Plugins/org.blueberry.ui.qt/src/berryISelectionService.cpp"
		},
		
		{
			"file" : "E:/D/MITK/Plugins/org.blueberry.ui.qt/src/berryIShellListener.cpp"
		},
		
		{
			"file" : "E:/D/MITK/Plugins/org.blueberry.ui.qt/src/berryIShellProvider.cpp"
		},
		
		{
			"file" : "E:/D/MITK/Plugins/org.blueberry.ui.qt/src/berryIShowInSource.h"
		},
		
		{
			"file" : "E:/D/MITK/Plugins/org.blueberry.ui.qt/src/berryIShowInTarget.h"
		},
		
		{
			"file" : "E:/D/MITK/Plugins/org.blueberry.ui.qt/src/berryISizeProvider.cpp"
		},
		
		{
			"file" : "E:/D/MITK/Plugins/org.blueberry.ui.qt/src/berryISourceProvider.cpp"
		},
		
		{
			"file" : "E:/D/MITK/Plugins/org.blueberry.ui.qt/src/berryISourceProviderListener.cpp"
		},
		
		{
			"file" : "E:/D/MITK/Plugins/org.blueberry.ui.qt/src/berryISources.cpp"
		},
		
		{
			"file" : "E:/D/MITK/Plugins/org.blueberry.ui.qt/src/berryIStickyViewDescriptor.cpp"
		},
		
		{
			"file" : "E:/D/MITK/Plugins/org.blueberry.ui.qt/src/berryIStructuredSelection.cpp"
		},
		
		{
			"file" : "E:/D/MITK/Plugins/org.blueberry.ui.qt/src/berryIViewCategory.cpp"
		},
		
		{
			"file" : "E:/D/MITK/Plugins/org.blueberry.ui.qt/src/berryIViewDescriptor.cpp"
		},
		
		{
			"file" : "E:/D/MITK/Plugins/org.blueberry.ui.qt/src/berryIViewLayout.cpp"
		},
		
		{
			"file" : "E:/D/MITK/Plugins/org.blueberry.ui.qt/src/berryIViewPart.cpp"
		},
		
		{
			"file" : "E:/D/MITK/Plugins/org.blueberry.ui.qt/src/berryIViewReference.cpp"
		},
		
		{
			"file" : "E:/D/MITK/Plugins/org.blueberry.ui.qt/src/berryIViewRegistry.cpp"
		},
		
		{
			"file" : "E:/D/MITK/Plugins/org.blueberry.ui.qt/src/berryIViewSite.cpp"
		},
		
		{
			"file" : "E:/D/MITK/Plugins/org.blueberry.ui.qt/src/berryIWorkbenchCommandConstants.cpp"
		},
		
		{
			"file" : "E:/D/MITK/Plugins/org.blueberry.ui.qt/src/berryIWindowListener.cpp"
		},
		
		{
			"file" : "E:/D/MITK/Plugins/org.blueberry.ui.qt/src/berryIWorkbench.cpp"
		},
		
		{
			"file" : "E:/D/MITK/Plugins/org.blueberry.ui.qt/src/berryIWorkbenchListener.cpp"
		},
		
		{
			"file" : "E:/D/MITK/Plugins/org.blueberry.ui.qt/src/berryIWorkbenchPage.cpp"
		},
		
		{
			"file" : "E:/D/MITK/Plugins/org.blueberry.ui.qt/src/berryIWorkbenchPart.cpp"
		},
		
		{
			"file" : "E:/D/MITK/Plugins/org.blueberry.ui.qt/src/berryIWorkbenchPartConstants.cpp"
		},
		
		{
			"file" : "E:/D/MITK/Plugins/org.blueberry.ui.qt/src/berryIWorkbenchPartDescriptor.cpp"
		},
		
		{
			"file" : "E:/D/MITK/Plugins/org.blueberry.ui.qt/src/berryIWorkbenchPartReference.cpp"
		},
		
		{
			"file" : "E:/D/MITK/Plugins/org.blueberry.ui.qt/src/berryIWorkbenchPartSite.cpp"
		},
		
		{
			"file" : "E:/D/MITK/Plugins/org.blueberry.ui.qt/src/berryIWorkbenchSite.cpp"
		},
		
		{
			"file" : "E:/D/MITK/Plugins/org.blueberry.ui.qt/src/berryIWorkbenchWindow.cpp"
		},
		
		{
			"file" : "E:/D/MITK/Plugins/org.blueberry.ui.qt/src/berryMenuUtil.cpp"
		},
		
		{
			"file" : "E:/D/MITK/Plugins/org.blueberry.ui.qt/src/berryPlatformUI.cpp"
		},
		
		{
			"file" : "E:/D/MITK/Plugins/org.blueberry.ui.qt/src/berryPropertyChangeEvent.cpp"
		},
		
		{
			"file" : "E:/D/MITK/Plugins/org.blueberry.ui.qt/src/berryQModelIndexObject.cpp"
		},
		
		{
			"file" : "E:/D/MITK/Plugins/org.blueberry.ui.qt/src/berryQtEditorPart.cpp"
		},
		
		{
			"file" : "E:/D/MITK/Plugins/org.blueberry.ui.qt/src/berryQtItemSelection.cpp"
		},
		
		{
			"file" : "E:/D/MITK/Plugins/org.blueberry.ui.qt/src/berryQtIntroPart.cpp"
		},
		
		{
			"file" : "E:/D/MITK/Plugins/org.blueberry.ui.qt/src/berryQtPreferences.cpp"
		},
		
		{
			"file" : "E:/D/MITK/Plugins/org.blueberry.ui.qt/src/berryQtSelectionProvider.cpp"
		},
		
		{
			"file" : "E:/D/MITK/Plugins/org.blueberry.ui.qt/src/berryQtViewPart.cpp"
		},
		
		{
			"file" : "E:/D/MITK/Plugins/org.blueberry.ui.qt/src/berrySameShellProvider.cpp"
		},
		
		{
			"file" : "E:/D/MITK/Plugins/org.blueberry.ui.qt/src/berrySaveable.cpp"
		},
		
		{
			"file" : "E:/D/MITK/Plugins/org.blueberry.ui.qt/src/berrySaveablesLifecycleEvent.cpp"
		},
		
		{
			"file" : "E:/D/MITK/Plugins/org.blueberry.ui.qt/src/berrySelectionChangedEvent.cpp"
		},
		
		{
			"file" : "E:/D/MITK/Plugins/org.blueberry.ui.qt/src/berryShell.cpp"
		},
		
		{
			"file" : "E:/D/MITK/Plugins/org.blueberry.ui.qt/src/berryShellEvent.cpp"
		},
		
		{
			"file" : "E:/D/MITK/Plugins/org.blueberry.ui.qt/src/berryShowInContext.cpp"
		},
		
		{
			"file" : "E:/D/MITK/Plugins/org.blueberry.ui.qt/src/berryUIException.cpp"
		},
		
		{
			"file" : "E:/D/MITK/Plugins/org.blueberry.ui.qt/src/berryViewPart.cpp"
		},
		
		{
			"file" : "E:/D/MITK/Plugins/org.blueberry.ui.qt/src/berryWindow.cpp"
		},
		
		{
			"file" : "E:/D/MITK/Plugins/org.blueberry.ui.qt/src/berryWorkbenchActionConstants.cpp"
		},
		
		{
			"file" : "E:/D/MITK/Plugins/org.blueberry.ui.qt/src/berryWorkbenchPart.cpp"
		},
		
		{
			"file" : "E:/D/MITK/Plugins/org.blueberry.ui.qt/src/berryWorkbenchPreferenceConstants.cpp"
		},
		
		{
			"file" : "E:/D/MITK/Plugins/org.blueberry.ui.qt/src/berryXMLMemento.cpp"
		},
		
		{
			"file" : "E:/D/MITK/Plugins/org.blueberry.ui.qt/src/actions/berryAbstractContributionFactory.cpp"
		},
		
		{
			"file" : "E:/D/MITK/Plugins/org.blueberry.ui.qt/src/actions/berryCommandContributionItem.cpp"
		},
		
		{
			"file" : "E:/D/MITK/Plugins/org.blueberry.ui.qt/src/actions/berryCommandContributionItemParameter.cpp"
		},
		
		{
			"file" : "E:/D/MITK/Plugins/org.blueberry.ui.qt/src/actions/berryContributionItem.cpp"
		},
		
		{
			"file" : "E:/D/MITK/Plugins/org.blueberry.ui.qt/src/actions/berryContributionItemFactory.cpp"
		},
		
		{
			"file" : "E:/D/MITK/Plugins/org.blueberry.ui.qt/src/actions/berryContributionManager.cpp"
		},
		
		{
			"file" : "E:/D/MITK/Plugins/org.blueberry.ui.qt/src/actions/berryGroupMarker.cpp"
		},
		
		{
			"file" : "E:/D/MITK/Plugins/org.blueberry.ui.qt/src/actions/berryIContributionItem.h"
		},
		
		{
			"file" : "E:/D/MITK/Plugins/org.blueberry.ui.qt/src/actions/berryIContributionManager.h"
		},
		
		{
			"file" : "E:/D/MITK/Plugins/org.blueberry.ui.qt/src/actions/berryIContributionManagerOverrides.cpp"
		},
		
		{
			"file" : "E:/D/MITK/Plugins/org.blueberry.ui.qt/src/actions/berryIMenuManager.h"
		},
		
		{
			"file" : "E:/D/MITK/Plugins/org.blueberry.ui.qt/src/actions/berryMenuManager.cpp"
		},
		
		{
			"file" : "E:/D/MITK/Plugins/org.blueberry.ui.qt/src/actions/berryQActionContributionItem.cpp"
		},
		
		{
			"file" : "E:/D/MITK/Plugins/org.blueberry.ui.qt/src/actions/berryQActionProperties.cpp"
		},
		
		{
			"file" : "E:/D/MITK/Plugins/org.blueberry.ui.qt/src/actions/berrySeparator.cpp"
		},
		
		{
			"file" : "E:/D/MITK/Plugins/org.blueberry.ui.qt/src/actions/berrySubContributionItem.cpp"
		},
		
		{
			"file" : "E:/D/MITK/Plugins/org.blueberry.ui.qt/src/application/berryActionBarAdvisor.cpp"
		},
		
		{
			"file" : "E:/D/MITK/Plugins/org.blueberry.ui.qt/src/application/berryIActionBarConfigurer.cpp"
		},
		
		{
			"file" : "E:/D/MITK/Plugins/org.blueberry.ui.qt/src/application/berryIWorkbenchConfigurer.cpp"
		},
		
		{
			"file" : "E:/D/MITK/Plugins/org.blueberry.ui.qt/src/application/berryIWorkbenchWindowConfigurer.cpp"
		},
		
		{
			"file" : "E:/D/MITK/Plugins/org.blueberry.ui.qt/src/application/berryWorkbenchAdvisor.cpp"
		},
		
		{
			"file" : "E:/D/MITK/Plugins/org.blueberry.ui.qt/src/application/berryWorkbenchWindowAdvisor.cpp"
		},
		
		{
			"file" : "E:/D/MITK/Plugins/org.blueberry.ui.qt/src/commands/berryICommandImageService.cpp"
		},
		
		{
			"file" : "E:/D/MITK/Plugins/org.blueberry.ui.qt/src/commands/berryICommandService.cpp"
		},
		
		{
			"file" : "E:/D/MITK/Plugins/org.blueberry.ui.qt/src/commands/berryIElementReference.h"
		},
		
		{
			"file" : "E:/D/MITK/Plugins/org.blueberry.ui.qt/src/commands/berryIElementUpdater.h"
		},
		
		{
			"file" : "E:/D/MITK/Plugins/org.blueberry.ui.qt/src/commands/berryIMenuService.h"
		},
		
		{
			"file" : "E:/D/MITK/Plugins/org.blueberry.ui.qt/src/commands/berryUIElement.cpp"
		},
		
		{
			"file" : "E:/D/MITK/Plugins/org.blueberry.ui.qt/src/guitk/berryGuiTkControlEvent.cpp"
		},
		
		{
			"file" : "E:/D/MITK/Plugins/org.blueberry.ui.qt/src/guitk/berryGuiTkEvent.cpp"
		},
		
		{
			"file" : "E:/D/MITK/Plugins/org.blueberry.ui.qt/src/guitk/berryGuiTkIControlListener.cpp"
		},
		
		{
			"file" : "E:/D/MITK/Plugins/org.blueberry.ui.qt/src/guitk/berryGuiTkISelectionListener.cpp"
		},
		
		{
			"file" : "E:/D/MITK/Plugins/org.blueberry.ui.qt/src/guitk/berryGuiTkSelectionEvent.cpp"
		},
		
		{
			"file" : "E:/D/MITK/Plugins/org.blueberry.ui.qt/src/handlers/berryHandlerUtil.cpp"
		},
		
		{
			"file" : "E:/D/MITK/Plugins/org.blueberry.ui.qt/src/handlers/berryIHandlerActivation.cpp"
		},
		
		{
			"file" : "E:/D/MITK/Plugins/org.blueberry.ui.qt/src/handlers/berryIHandlerService.cpp"
		},
		
		{
			"file" : "E:/D/MITK/Plugins/org.blueberry.ui.qt/src/handlers/berryRadioState.cpp"
		},
		
		{
			"file" : "E:/D/MITK/Plugins/org.blueberry.ui.qt/src/handlers/berryRegistryToggleState.cpp"
		},
		
		{
			"file" : "E:/D/MITK/Plugins/org.blueberry.ui.qt/src/handlers/berryToggleState.cpp"
		},
		
		{
			"file" : "E:/D/MITK/Plugins/org.blueberry.ui.qt/src/intro/berryIIntroManager.cpp"
		},
		
		{
			"file" : "E:/D/MITK/Plugins/org.blueberry.ui.qt/src/intro/berryIIntroPart.cpp"
		},
		
		{
			"file" : "E:/D/MITK/Plugins/org.blueberry.ui.qt/src/intro/berryIIntroSite.cpp"
		},
		
		{
			"file" : "E:/D/MITK/Plugins/org.blueberry.ui.qt/src/intro/berryIntroPart.cpp"
		},
		
		{
			"file" : "E:/D/MITK/Plugins/org.blueberry.ui.qt/src/model/berryPerspectiveListModel.cpp"
		},
		
		{
			"file" : "E:/D/MITK/Plugins/org.blueberry.ui.qt/src/model/berryViewTreeModel.cpp"
		},
		
		{
			"file" : "E:/D/MITK/Plugins/org.blueberry.ui.qt/src/tweaklets/berryGuiWidgetsTweaklet.cpp"
		},
		
		{
			"file" : "E:/D/MITK/Plugins/org.blueberry.ui.qt/src/tweaklets/berryWorkbenchPageTweaklet.cpp"
		},
		
		{
			"file" : "E:/D/MITK/Plugins/org.blueberry.ui.qt/src/tweaklets/berryWorkbenchTweaklet.cpp"
		},
		
		{
			"file" : "E:/D/MITK/Plugins/org.blueberry.ui.qt/src/presentations/berryIPresentablePart.cpp"
		},
		
		{
			"file" : "E:/D/MITK/Plugins/org.blueberry.ui.qt/src/presentations/berryIPresentationFactory.cpp"
		},
		
		{
			"file" : "E:/D/MITK/Plugins/org.blueberry.ui.qt/src/presentations/berryIPresentationSerializer.cpp"
		},
		
		{
			"file" : "E:/D/MITK/Plugins/org.blueberry.ui.qt/src/presentations/berryIStackPresentationSite.cpp"
		},
		
		{
			"file" : "E:/D/MITK/Plugins/org.blueberry.ui.qt/src/presentations/berryStackDropResult.cpp"
		},
		
		{
			"file" : "E:/D/MITK/Plugins/org.blueberry.ui.qt/src/presentations/berryStackPresentation.cpp"
		},
		
		{
			"file" : "E:/D/MITK/Plugins/org.blueberry.ui.qt/src/services/berryIDisposable.cpp"
		},
		
		{
			"file" : "E:/D/MITK/Plugins/org.blueberry.ui.qt/src/services/berryIEvaluationReference.h"
		},
		
		{
			"file" : "E:/D/MITK/Plugins/org.blueberry.ui.qt/src/services/berryIEvaluationService.cpp"
		},
		
		{
			"file" : "E:/D/MITK/Plugins/org.blueberry.ui.qt/src/services/berryINestable.cpp"
		},
		
		{
			"file" : "E:/D/MITK/Plugins/org.blueberry.ui.qt/src/services/berryIServiceFactory.cpp"
		},
		
		{
			"file" : "E:/D/MITK/Plugins/org.blueberry.ui.qt/src/services/berryIServiceLocator.cpp"
		},
		
		{
			"file" : "E:/D/MITK/Plugins/org.blueberry.ui.qt/src/services/berryIServiceScopes.cpp"
		},
		
		{
			"file" : "E:/D/MITK/Plugins/org.blueberry.ui.qt/src/services/berryIServiceWithSources.cpp"
		},
		
		{
			"file" : "E:/D/MITK/Plugins/org.blueberry.ui.qt/src/services/berryISourceProviderService.cpp"
		},
		
		{
			"file" : "E:/D/MITK/Plugins/org.blueberry.ui.qt/src/testing/berryTestableObject.cpp"
		},
		
		{
			"file" : "E:/D/MITK/Plugins/org.blueberry.ui.qt/src/util/berryISafeRunnableRunner.cpp"
		},
		
		{
			"file" : "E:/D/MITK/Plugins/org.blueberry.ui.qt/src/util/berrySafeRunnable.cpp"
		},
		
		{
			"file" : "E:/D/MITK/Plugins/org.blueberry.ui.qt/src/application/berryQtWorkbenchAdvisor.cpp"
		},
		
		{
			"file" : "E:/D/MITK/Plugins/org.blueberry.ui.qt/src/internal/defaultpresentation/berryEmptyTabFolder.cpp"
		},
		
		{
			"file" : "E:/D/MITK/Plugins/org.blueberry.ui.qt/src/internal/defaultpresentation/berryEmptyTabItem.cpp"
		},
		
		{
			"file" : "E:/D/MITK/Plugins/org.blueberry.ui.qt/src/internal/defaultpresentation/berryNativeTabFolder.cpp"
		},
		
		{
			"file" : "E:/D/MITK/Plugins/org.blueberry.ui.qt/src/internal/defaultpresentation/berryNativeTabItem.cpp"
		},
		
		{
			"file" : "E:/D/MITK/Plugins/org.blueberry.ui.qt/src/internal/defaultpresentation/berryQCTabBar.cpp"
		},
		
		{
			"file" : "E:/D/MITK/Plugins/org.blueberry.ui.qt/src/internal/defaultpresentation/berryQtWorkbenchPresentationFactory.cpp"
		},
		
		{
			"file" : "E:/D/MITK/Plugins/org.blueberry.ui.qt/src/internal/dialogs/berryPerspectivesPreferencePage.cpp"
		},
		
		{
			"file" : "E:/D/MITK/Plugins/org.blueberry.ui.qt/src/internal/dialogs/berrySavePerspectiveDialog.cpp"
		},
		
		{
			"file" : "E:/D/MITK/Plugins/org.blueberry.ui.qt/src/internal/handlers/berryCloseAllPerspectivesHandler.cpp"
		},
		
		{
			"file" : "E:/D/MITK/Plugins/org.blueberry.ui.qt/src/internal/handlers/berryClosePerspectiveHandler.cpp"
		},
		
		{
			"file" : "E:/D/MITK/Plugins/org.blueberry.ui.qt/src/internal/handlers/berryDynamicHelpHandler.cpp"
		},
		
		{
			"file" : "E:/D/MITK/Plugins/org.blueberry.ui.qt/src/internal/handlers/berryHelpContentsHandler.cpp"
		},
		
		{
			"file" : "E:/D/MITK/Plugins/org.blueberry.ui.qt/src/internal/handlers/berryIntroHandler.cpp"
		},
		
		{
			"file" : "E:/D/MITK/Plugins/org.blueberry.ui.qt/src/internal/handlers/berryNewEditorHandler.cpp"
		},
		
		{
			"file" : "E:/D/MITK/Plugins/org.blueberry.ui.qt/src/internal/handlers/berryOpenInNewWindowHandler.cpp"
		},
		
		{
			"file" : "E:/D/MITK/Plugins/org.blueberry.ui.qt/src/internal/handlers/berryQuitHandler.cpp"
		},
		
		{
			"file" : "E:/D/MITK/Plugins/org.blueberry.ui.qt/src/internal/handlers/berryResetPerspectiveHandler.cpp"
		},
		
		{
			"file" : "E:/D/MITK/Plugins/org.blueberry.ui.qt/src/internal/handlers/berrySavePerspectiveHandler.cpp"
		},
		
		{
			"file" : "E:/D/MITK/Plugins/org.blueberry.ui.qt/src/internal/handlers/berryShowPerspectiveHandler.cpp"
		},
		
		{
			"file" : "E:/D/MITK/Plugins/org.blueberry.ui.qt/src/internal/handlers/berryShowViewHandler.cpp"
		},
		
		{
			"file" : "E:/D/MITK/Plugins/org.blueberry.ui.qt/src/internal/util/berryAbstractTabFolder.cpp"
		},
		
		{
			"file" : "E:/D/MITK/Plugins/org.blueberry.ui.qt/src/internal/util/berryAbstractTabItem.cpp"
		},
		
		{
			"file" : "E:/D/MITK/Plugins/org.blueberry.ui.qt/src/internal/util/berryIPresentablePartList.cpp"
		},
		
		{
			"file" : "E:/D/MITK/Plugins/org.blueberry.ui.qt/src/internal/util/berryLeftToRightTabOrder.cpp"
		},
		
		{
			"file" : "E:/D/MITK/Plugins/org.blueberry.ui.qt/src/internal/util/berryPartInfo.cpp"
		},
		
		{
			"file" : "E:/D/MITK/Plugins/org.blueberry.ui.qt/src/internal/util/berryPresentablePartFolder.cpp"
		},
		
		{
			"file" : "E:/D/MITK/Plugins/org.blueberry.ui.qt/src/internal/util/berryReplaceDragHandler.cpp"
		},
		
		{
			"file" : "E:/D/MITK/Plugins/org.blueberry.ui.qt/src/internal/util/berryTabbedStackPresentation.cpp"
		},
		
		{
			"file" : "E:/D/MITK/Plugins/org.blueberry.ui.qt/src/internal/util/berryTabDragHandler.cpp"
		},
		
		{
			"file" : "E:/D/MITK/Plugins/org.blueberry.ui.qt/src/internal/util/berryTabFolderEvent.cpp"
		},
		
		{
			"file" : "E:/D/MITK/Plugins/org.blueberry.ui.qt/src/internal/util/berryTabOrder.cpp"
		},
		
		{
			"file" : "E:/D/MITK/Plugins/org.blueberry.ui.qt/src/internal/intro/berryEditorIntroAdapterPart.cpp"
		},
		
		{
			"file" : "E:/D/MITK/Plugins/org.blueberry.ui.qt/src/internal/intro/berryIIntroDescriptor.cpp"
		},
		
		{
			"file" : "E:/D/MITK/Plugins/org.blueberry.ui.qt/src/internal/intro/berryIIntroRegistry.cpp"
		},
		
		{
			"file" : "E:/D/MITK/Plugins/org.blueberry.ui.qt/src/internal/intro/berryIntroConstants.cpp"
		},
		
		{
			"file" : "E:/D/MITK/Plugins/org.blueberry.ui.qt/src/internal/intro/berryIntroDescriptor.cpp"
		},
		
		{
			"file" : "E:/D/MITK/Plugins/org.blueberry.ui.qt/src/internal/intro/berryIntroPartAdapterSite.cpp"
		},
		
		{
			"file" : "E:/D/MITK/Plugins/org.blueberry.ui.qt/src/internal/intro/berryIntroRegistry.cpp"
		},
		
		{
			"file" : "E:/D/MITK/Plugins/org.blueberry.ui.qt/src/internal/intro/berryViewIntroAdapterPart.cpp"
		},
		
		{
			"file" : "E:/D/MITK/Plugins/org.blueberry.ui.qt/src/internal/intro/berryWorkbenchIntroManager.cpp"
		},
		
		{
			"file" : "E:/D/MITK/Plugins/org.blueberry.ui.qt/src/internal/berryAbstractGroupMarker.cpp"
		},
		
		{
			"file" : "E:/D/MITK/Plugins/org.blueberry.ui.qt/src/internal/berryAbstractMenuAdditionCacheEntry.cpp"
		},
		
		{
			"file" : "E:/D/MITK/Plugins/org.blueberry.ui.qt/src/internal/berryAbstractPartSelectionTracker.cpp"
		},
		
		{
			"file" : "E:/D/MITK/Plugins/org.blueberry.ui.qt/src/internal/berryAbstractSelectionService.cpp"
		},
		
		{
			"file" : "E:/D/MITK/Plugins/org.blueberry.ui.qt/src/internal/berryActivePartExpression.cpp"
		},
		
		{
			"file" : "E:/D/MITK/Plugins/org.blueberry.ui.qt/src/internal/berryAlwaysEnabledExpression.cpp"
		},
		
		{
			"file" : "E:/D/MITK/Plugins/org.blueberry.ui.qt/src/internal/berryAndExpression.cpp"
		},
		
		{
			"file" : "E:/D/MITK/Plugins/org.blueberry.ui.qt/src/internal/berryBundleUtility.cpp"
		},
		
		{
			"file" : "E:/D/MITK/Plugins/org.blueberry.ui.qt/src/internal/berryChangeToPerspectiveMenu.cpp"
		},
		
		{
			"file" : "E:/D/MITK/Plugins/org.blueberry.ui.qt/src/internal/berryCommandParameter.cpp"
		},
		
		{
			"file" : "E:/D/MITK/Plugins/org.blueberry.ui.qt/src/internal/berryCommandPersistence.cpp"
		},
		
		{
			"file" : "E:/D/MITK/Plugins/org.blueberry.ui.qt/src/internal/berryCommandService.cpp"
		},
		
		{
			"file" : "E:/D/MITK/Plugins/org.blueberry.ui.qt/src/internal/berryCommandServiceFactory.cpp"
		},
		
		{
			"file" : "E:/D/MITK/Plugins/org.blueberry.ui.qt/src/internal/berryCommandStateProxy.cpp"
		},
		
		{
			"file" : "E:/D/MITK/Plugins/org.blueberry.ui.qt/src/internal/berryCompositeExpression.cpp"
		},
		
		{
			"file" : "E:/D/MITK/Plugins/org.blueberry.ui.qt/src/internal/berryContainerPlaceholder.cpp"
		},
		
		{
			"file" : "E:/D/MITK/Plugins/org.blueberry.ui.qt/src/internal/berryContributionRoot.cpp"
		},
		
		{
			"file" : "E:/D/MITK/Plugins/org.blueberry.ui.qt/src/internal/berryDetachedPlaceHolder.cpp"
		},
		
		{
			"file" : "E:/D/MITK/Plugins/org.blueberry.ui.qt/src/internal/berryDefaultSaveable.cpp"
		},
		
		{
			"file" : "E:/D/MITK/Plugins/org.blueberry.ui.qt/src/internal/berryDefaultStackPresentationSite.cpp"
		},
		
		{
			"file" : "E:/D/MITK/Plugins/org.blueberry.ui.qt/src/internal/berryDetachedWindow.cpp"
		},
		
		{
			"file" : "E:/D/MITK/Plugins/org.blueberry.ui.qt/src/internal/berryDirtyPerspectiveMarker.cpp"
		},
		
		{
			"file" : "E:/D/MITK/Plugins/org.blueberry.ui.qt/src/internal/berryDragUtil.cpp"
		},
		
		{
			"file" : "E:/D/MITK/Plugins/org.blueberry.ui.qt/src/internal/berryEditorAreaHelper.cpp"
		},
		
		{
			"file" : "E:/D/MITK/Plugins/org.blueberry.ui.qt/src/internal/berryEditorDescriptor.cpp"
		},
		
		{
			"file" : "E:/D/MITK/Plugins/org.blueberry.ui.qt/src/internal/berryEditorHistory.cpp"
		},
		
		{
			"file" : "E:/D/MITK/Plugins/org.blueberry.ui.qt/src/internal/berryEditorHistoryItem.cpp"
		},
		
		{
			"file" : "E:/D/MITK/Plugins/org.blueberry.ui.qt/src/internal/berryEditorManager.cpp"
		},
		
		{
			"file" : "E:/D/MITK/Plugins/org.blueberry.ui.qt/src/internal/berryEditorReference.cpp"
		},
		
		{
			"file" : "E:/D/MITK/Plugins/org.blueberry.ui.qt/src/internal/berryEditorRegistry.cpp"
		},
		
		{
			"file" : "E:/D/MITK/Plugins/org.blueberry.ui.qt/src/internal/berryEditorRegistryReader.cpp"
		},
		
		{
			"file" : "E:/D/MITK/Plugins/org.blueberry.ui.qt/src/internal/berryEditorSashContainer.cpp"
		},
		
		{
			"file" : "E:/D/MITK/Plugins/org.blueberry.ui.qt/src/internal/berryEditorSite.cpp"
		},
		
		{
			"file" : "E:/D/MITK/Plugins/org.blueberry.ui.qt/src/internal/berryElementReference.cpp"
		},
		
		{
			"file" : "E:/D/MITK/Plugins/org.blueberry.ui.qt/src/internal/berryErrorViewPart.cpp"
		},
		
		{
			"file" : "E:/D/MITK/Plugins/org.blueberry.ui.qt/src/internal/berryEvaluationAuthority.cpp"
		},
		
		{
			"file" : "E:/D/MITK/Plugins/org.blueberry.ui.qt/src/internal/berryEvaluationReference.cpp"
		},
		
		{
			"file" : "E:/D/MITK/Plugins/org.blueberry.ui.qt/src/internal/berryEvaluationResultCache.cpp"
		},
		
		{
			"file" : "E:/D/MITK/Plugins/org.blueberry.ui.qt/src/internal/berryEvaluationService.cpp"
		},
		
		{
			"file" : "E:/D/MITK/Plugins/org.blueberry.ui.qt/src/internal/berryExpressionAuthority.cpp"
		},
		
		{
			"file" : "E:/D/MITK/Plugins/org.blueberry.ui.qt/src/internal/berryFileEditorMapping.cpp"
		},
		
		{
			"file" : "E:/D/MITK/Plugins/org.blueberry.ui.qt/src/internal/berryFolderLayout.cpp"
		},
		
		{
			"file" : "E:/D/MITK/Plugins/org.blueberry.ui.qt/src/internal/berryHandlerActivation.cpp"
		},
		
		{
			"file" : "E:/D/MITK/Plugins/org.blueberry.ui.qt/src/internal/berryHandlerAuthority.cpp"
		},
		
		{
			"file" : "E:/D/MITK/Plugins/org.blueberry.ui.qt/src/internal/berryHandlerPersistence.cpp"
		},
		
		{
			"file" : "E:/D/MITK/Plugins/org.blueberry.ui.qt/src/internal/berryHandlerProxy.cpp"
		},
		
		{
			"file" : "E:/D/MITK/Plugins/org.blueberry.ui.qt/src/internal/berryHandlerService.cpp"
		},
		
		{
			"file" : "E:/D/MITK/Plugins/org.blueberry.ui.qt/src/internal/berryHandlerServiceFactory.cpp"
		},
		
		{
			"file" : "E:/D/MITK/Plugins/org.blueberry.ui.qt/src/internal/berryIDragOverListener.cpp"
		},
		
		{
			"file" : "E:/D/MITK/Plugins/org.blueberry.ui.qt/src/internal/berryIDropTarget.cpp"
		},
		
		{
			"file" : "E:/D/MITK/Plugins/org.blueberry.ui.qt/src/internal/berryIEvaluationResultCache.cpp"
		},
		
		{
			"file" : "E:/D/MITK/Plugins/org.blueberry.ui.qt/src/internal/berryILayoutContainer.cpp"
		},
		
		{
			"file" : "E:/D/MITK/Plugins/org.blueberry.ui.qt/src/internal/berryInternalMenuService.h"
		},
		
		{
			"file" : "E:/D/MITK/Plugins/org.blueberry.ui.qt/src/internal/berryIServiceLocatorCreator.cpp"
		},
		
		{
			"file" : "E:/D/MITK/Plugins/org.blueberry.ui.qt/src/internal/berryIStickyViewManager.cpp"
		},
		
		{
			"file" : "E:/D/MITK/Plugins/org.blueberry.ui.qt/src/internal/berryIWorkbenchLocationService.cpp"
		},
		
		{
			"file" : "E:/D/MITK/Plugins/org.blueberry.ui.qt/src/internal/berryKeywordRegistry.cpp"
		},
		
		{
			"file" : "E:/D/MITK/Plugins/org.blueberry.ui.qt/src/internal/berryLayoutHelper.cpp"
		},
		
		{
			"file" : "E:/D/MITK/Plugins/org.blueberry.ui.qt/src/internal/berryLayoutPart.cpp"
		},
		
		{
			"file" : "E:/D/MITK/Plugins/org.blueberry.ui.qt/src/internal/berryLayoutPartSash.cpp"
		},
		
		{
			"file" : "E:/D/MITK/Plugins/org.blueberry.ui.qt/src/internal/berryLayoutTree.cpp"
		},
		
		{
			"file" : "E:/D/MITK/Plugins/org.blueberry.ui.qt/src/internal/berryLayoutTreeNode.cpp"
		},
		
		{
			"file" : "E:/D/MITK/Plugins/org.blueberry.ui.qt/src/internal/berryMenuServiceFactory.cpp"
		},
		
		{
			"file" : "E:/D/MITK/Plugins/org.blueberry.ui.qt/src/internal/berryNestableHandlerService.cpp"
		},
		
		{
			"file" : "E:/D/MITK/Plugins/org.blueberry.ui.qt/src/internal/berryNullEditorInput.cpp"
		},
		
		{
			"file" : "E:/D/MITK/Plugins/org.blueberry.ui.qt/src/internal/berryOpenPerspectivePropertyTester.cpp"
		},
		
		{
			"file" : "E:/D/MITK/Plugins/org.blueberry.ui.qt/src/internal/berryPageLayout.cpp"
		},
		
		{
			"file" : "E:/D/MITK/Plugins/org.blueberry.ui.qt/src/internal/berryPagePartSelectionTracker.cpp"
		},
		
		{
			"file" : "E:/D/MITK/Plugins/org.blueberry.ui.qt/src/internal/berryPageSelectionService.cpp"
		},
		
		{
			"file" : "E:/D/MITK/Plugins/org.blueberry.ui.qt/src/internal/berryParameterValueConverterProxy.cpp"
		},
		
		{
			"file" : "E:/D/MITK/Plugins/org.blueberry.ui.qt/src/internal/berryPartList.cpp"
		},
		
		{
			"file" : "E:/D/MITK/Plugins/org.blueberry.ui.qt/src/internal/berryPartPane.cpp"
		},
		
		{
			"file" : "E:/D/MITK/Plugins/org.blueberry.ui.qt/src/internal/berryPartPlaceholder.cpp"
		},
		
		{
			"file" : "E:/D/MITK/Plugins/org.blueberry.ui.qt/src/internal/berryPartSashContainer.cpp"
		},
		
		{
			"file" : "E:/D/MITK/Plugins/org.blueberry.ui.qt/src/internal/berryPartService.cpp"
		},
		
		{
			"file" : "E:/D/MITK/Plugins/org.blueberry.ui.qt/src/internal/berryPartSite.cpp"
		},
		
		{
			"file" : "E:/D/MITK/Plugins/org.blueberry.ui.qt/src/internal/berryPartStack.cpp"
		},
		
		{
			"file" : "E:/D/MITK/Plugins/org.blueberry.ui.qt/src/internal/berryPartTester.cpp"
		},
		
		{
			"file" : "E:/D/MITK/Plugins/org.blueberry.ui.qt/src/internal/berryPersistentState.cpp"
		},
		
		{
			"file" : "E:/D/MITK/Plugins/org.blueberry.ui.qt/src/internal/berryPerspective.cpp"
		},
		
		{
			"file" : "E:/D/MITK/Plugins/org.blueberry.ui.qt/src/internal/berryPerspectiveDescriptor.cpp"
		},
		
		{
			"file" : "E:/D/MITK/Plugins/org.blueberry.ui.qt/src/internal/berryPerspectiveExtensionReader.cpp"
		},
		
		{
			"file" : "E:/D/MITK/Plugins/org.blueberry.ui.qt/src/internal/berryPerspectiveHelper.cpp"
		},
		
		{
			"file" : "E:/D/MITK/Plugins/org.blueberry.ui.qt/src/internal/berryPerspectiveParameterValues.cpp"
		},
		
		{
			"file" : "E:/D/MITK/Plugins/org.blueberry.ui.qt/src/internal/berryPerspectiveRegistry.cpp"
		},
		
		{
			"file" : "E:/D/MITK/Plugins/org.blueberry.ui.qt/src/internal/berryPerspectiveRegistryReader.cpp"
		},
		
		{
			"file" : "E:/D/MITK/Plugins/org.blueberry.ui.qt/src/internal/berryPlaceholderFolderLayout.cpp"
		},
		
		{
			"file" : "E:/D/MITK/Plugins/org.blueberry.ui.qt/src/internal/berryPolicy.cpp"
		},
		
		{
			"file" : "E:/D/MITK/Plugins/org.blueberry.ui.qt/src/internal/berryPreferenceConstants.cpp"
		},
		
		{
			"file" : "E:/D/MITK/Plugins/org.blueberry.ui.qt/src/internal/berryPreferencePageParameterValues.cpp"
		},
		
		{
			"file" : "E:/D/MITK/Plugins/org.blueberry.ui.qt/src/internal/berryPresentablePart.cpp"
		},
		
		{
			"file" : "E:/D/MITK/Plugins/org.blueberry.ui.qt/src/internal/berryPresentationFactoryUtil.cpp"
		},
		
		{
			"file" : "E:/D/MITK/Plugins/org.blueberry.ui.qt/src/internal/berryPresentationSerializer.cpp"
		},
		
		{
			"file" : "E:/D/MITK/Plugins/org.blueberry.ui.qt/src/internal/berryQtControlWidget.cpp"
		},
		
		{
			"file" : "E:/D/MITK/Plugins/org.blueberry.ui.qt/src/internal/berryQtDnDControlWidget.cpp"
		},
		
		{
			"file" : "E:/D/MITK/Plugins/org.blueberry.ui.qt/src/internal/berryQtDisplay.cpp"
		},
		
		{
			"file" : "E:/D/MITK/Plugins/org.blueberry.ui.qt/src/internal/berryQtGlobalEventFilter.cpp"
		},
		
		{
			"file" : "E:/D/MITK/Plugins/org.blueberry.ui.qt/src/internal/berryQtMainWindowControl.cpp"
		},
		
		{
			"file" : "E:/D/MITK/Plugins/org.blueberry.ui.qt/src/internal/berryQtOpenPerspectiveAction.cpp"
		},
		
		{
			"file" : "E:/D/MITK/Plugins/org.blueberry.ui.qt/src/internal/berryQtPerspectiveSwitcher.cpp"
		},
		
		{
			"file" : "E:/D/MITK/Plugins/org.blueberry.ui.qt/src/internal/berryQtSash.cpp"
		},
		
		{
			"file" : "E:/D/MITK/Plugins/org.blueberry.ui.qt/src/internal/berryQtShell.cpp"
		},
		
		{
			"file" : "E:/D/MITK/Plugins/org.blueberry.ui.qt/src/internal/berryQtShowPerspectiveDialog.cpp"
		},
		
		{
			"file" : "E:/D/MITK/Plugins/org.blueberry.ui.qt/src/internal/berryQtShowViewAction.cpp"
		},
		
		{
			"file" : "E:/D/MITK/Plugins/org.blueberry.ui.qt/src/internal/berryQtShowViewDialog.cpp"
		},
		
		{
			"file" : "E:/D/MITK/Plugins/org.blueberry.ui.qt/src/internal/berryQtStyleManager.cpp"
		},
		
		{
			"file" : "E:/D/MITK/Plugins/org.blueberry.ui.qt/src/internal/berryQtStylePreferencePage.cpp"
		},
		
		{
			"file" : "E:/D/MITK/Plugins/org.blueberry.ui.qt/src/internal/berryQtTracker.cpp"
		},
		
		{
			"file" : "E:/D/MITK/Plugins/org.blueberry.ui.qt/src/internal/berryQtWidgetController.cpp"
		},
		
		{
			"file" : "E:/D/MITK/Plugins/org.blueberry.ui.qt/src/internal/berryQtWidgetsTweaklet.cpp"
		},
		
		{
			"file" : "E:/D/MITK/Plugins/org.blueberry.ui.qt/src/internal/berryQtWidgetsTweakletImpl.cpp"
		},
		
		{
			"file" : "E:/D/MITK/Plugins/org.blueberry.ui.qt/src/internal/berryQtWorkbenchPageTweaklet.cpp"
		},
		
		{
			"file" : "E:/D/MITK/Plugins/org.blueberry.ui.qt/src/internal/berryQtWorkbenchTweaklet.cpp"
		},
		
		{
			"file" : "E:/D/MITK/Plugins/org.blueberry.ui.qt/src/internal/berryRegistryPersistence.cpp"
		},
		
		{
			"file" : "E:/D/MITK/Plugins/org.blueberry.ui.qt/src/internal/berryRegistryReader.cpp"
		},
		
		{
			"file" : "E:/D/MITK/Plugins/org.blueberry.ui.qt/src/internal/berryReopenEditorMenu.cpp"
		},
		
		{
			"file" : "E:/D/MITK/Plugins/org.blueberry.ui.qt/src/internal/berrySaveablesList.cpp"
		},
		
		{
			"file" : "E:/D/MITK/Plugins/org.blueberry.ui.qt/src/internal/berryShowViewMenu.cpp"
		},
		
		{
			"file" : "E:/D/MITK/Plugins/org.blueberry.ui.qt/src/internal/berryServiceLocator.cpp"
		},
		
		{
			"file" : "E:/D/MITK/Plugins/org.blueberry.ui.qt/src/internal/berryServiceLocatorCreator.cpp"
		},
		
		{
			"file" : "E:/D/MITK/Plugins/org.blueberry.ui.qt/src/internal/berryShellPool.cpp"
		},
		
		{
			"file" : "E:/D/MITK/Plugins/org.blueberry.ui.qt/src/internal/berrySlaveCommandService.cpp"
		},
		
		{
			"file" : "E:/D/MITK/Plugins/org.blueberry.ui.qt/src/internal/berrySlaveHandlerService.cpp"
		},
		
		{
			"file" : "E:/D/MITK/Plugins/org.blueberry.ui.qt/src/internal/berrySlaveMenuService.cpp"
		},
		
		{
			"file" : "E:/D/MITK/Plugins/org.blueberry.ui.qt/src/internal/berrySourceProviderService.cpp"
		},
		
		{
			"file" : "E:/D/MITK/Plugins/org.blueberry.ui.qt/src/internal/berrySourcePriorityNameMapping.cpp"
		},
		
		{
			"file" : "E:/D/MITK/Plugins/org.blueberry.ui.qt/src/internal/berryStatusUtil.cpp"
		},
		
		{
			"file" : "E:/D/MITK/Plugins/org.blueberry.ui.qt/src/internal/berryStickyViewDescriptor.cpp"
		},
		
		{
			"file" : "E:/D/MITK/Plugins/org.blueberry.ui.qt/src/internal/berryStickyViewManager.cpp"
		},
		
		{
			"file" : "E:/D/MITK/Plugins/org.blueberry.ui.qt/src/internal/berrySwitchToWindowMenu.cpp"
		},
		
		{
			"file" : "E:/D/MITK/Plugins/org.blueberry.ui.qt/src/internal/berryTweaklets.cpp"
		},
		
		{
			"file" : "E:/D/MITK/Plugins/org.blueberry.ui.qt/src/internal/berryUIExtensionTracker.cpp"
		},
		
		{
			"file" : "E:/D/MITK/Plugins/org.blueberry.ui.qt/src/internal/berryUtil.cpp"
		},
		
		{
			"file" : "E:/D/MITK/Plugins/org.blueberry.ui.qt/src/internal/berryViewDescriptor.cpp"
		},
		
		{
			"file" : "E:/D/MITK/Plugins/org.blueberry.ui.qt/src/internal/berryViewFactory.cpp"
		},
		
		{
			"file" : "E:/D/MITK/Plugins/org.blueberry.ui.qt/src/internal/berryViewLayout.cpp"
		},
		
		{
			"file" : "E:/D/MITK/Plugins/org.blueberry.ui.qt/src/internal/berryViewReference.cpp"
		},
		
		{
			"file" : "E:/D/MITK/Plugins/org.blueberry.ui.qt/src/internal/berryViewRegistry.cpp"
		},
		
		{
			"file" : "E:/D/MITK/Plugins/org.blueberry.ui.qt/src/internal/berryViewRegistryReader.cpp"
		},
		
		{
			"file" : "E:/D/MITK/Plugins/org.blueberry.ui.qt/src/internal/berryViewSashContainer.cpp"
		},
		
		{
			"file" : "E:/D/MITK/Plugins/org.blueberry.ui.qt/src/internal/berryViewSite.cpp"
		},
		
		{
			"file" : "E:/D/MITK/Plugins/org.blueberry.ui.qt/src/internal/berryWorkbenchPage.cpp"
		},
		
		{
			"file" : "E:/D/MITK/Plugins/org.blueberry.ui.qt/src/internal/berryWindowManager.cpp"
		},
		
		{
			"file" : "E:/D/MITK/Plugins/org.blueberry.ui.qt/src/internal/berryWindowPartSelectionTracker.cpp"
		},
		
		{
			"file" : "E:/D/MITK/Plugins/org.blueberry.ui.qt/src/internal/berryWindowSelectionService.cpp"
		},
		
		{
			"file" : "E:/D/MITK/Plugins/org.blueberry.ui.qt/src/internal/berryWorkbench.cpp"
		},
		
		{
			"file" : "E:/D/MITK/Plugins/org.blueberry.ui.qt/src/internal/berryWorkbenchConfigurer.cpp"
		},
		
		{
			"file" : "E:/D/MITK/Plugins/org.blueberry.ui.qt/src/internal/berryWorkbenchConstants.cpp"
		},
		
		{
			"file" : "E:/D/MITK/Plugins/org.blueberry.ui.qt/src/internal/berryWorkbenchLocationService.cpp"
		},
		
		{
			"file" : "E:/D/MITK/Plugins/org.blueberry.ui.qt/src/internal/berryWorkbenchMenuService.cpp"
		},
		
		{
			"file" : "E:/D/MITK/Plugins/org.blueberry.ui.qt/src/internal/berryWorkbenchPagePartList.cpp"
		},
		
		{
			"file" : "E:/D/MITK/Plugins/org.blueberry.ui.qt/src/internal/berryWorkbenchPartReference.cpp"
		},
		
		{
			"file" : "E:/D/MITK/Plugins/org.blueberry.ui.qt/src/internal/berryWorkbenchPlugin.cpp"
		},
		
		{
			"file" : "E:/D/MITK/Plugins/org.blueberry.ui.qt/src/internal/berryWorkbenchRegistryConstants.cpp"
		},
		
		{
			"file" : "E:/D/MITK/Plugins/org.blueberry.ui.qt/src/internal/berryWorkbenchServiceRegistry.cpp"
		},
		
		{
			"file" : "E:/D/MITK/Plugins/org.blueberry.ui.qt/src/internal/berryWorkbenchSourceProvider.cpp"
		},
		
		{
			"file" : "E:/D/MITK/Plugins/org.blueberry.ui.qt/src/internal/berryWorkbenchTestable.cpp"
		},
		
		{
			"file" : "E:/D/MITK/Plugins/org.blueberry.ui.qt/src/internal/berryWorkbenchWindow.cpp"
		},
		
		{
			"file" : "E:/D/MITK/Plugins/org.blueberry.ui.qt/src/internal/berryWorkbenchWindowConfigurer.cpp"
		},
		
		{
			"file" : "E:/D/MITK/Plugins/org.blueberry.ui.qt/src/internal/berryWorkbenchWindowExpression.cpp"
		},
		
		{
			"file" : "E:/D/MITK/Plugins/org.blueberry.ui.qt/src/internal/berryWWinActionBars.cpp"
		},
		
		{
			"file" : "E:/D/MITK/Plugins/org.blueberry.ui.qt/src/internal/berryWWinPartService.cpp"
		},
		
		{
			"file" : "E:/D/MITK/Plugins/org.blueberry.ui.qt/src/berryAbstractSourceProvider.h"
		},
		
		{
			"file" : "E:/D/MITK/Plugins/org.blueberry.ui.qt/src/berryAbstractUICTKPlugin.h"
		},
		
		{
			"file" : "E:/D/MITK/Plugins/org.blueberry.ui.qt/src/berryConstants.h"
		},
		
		{
			"file" : "E:/D/MITK/Plugins/org.blueberry.ui.qt/src/berryDisplay.h"
		},
		
		{
			"file" : "E:/D/MITK/Plugins/org.blueberry.ui.qt/src/berryEditorPart.h"
		},
		
		{
			"file" : "E:/D/MITK/Plugins/org.blueberry.ui.qt/src/berryExtensionFactory.h"
		},
		
		{
			"file" : "E:/D/MITK/Plugins/org.blueberry.ui.qt/src/berryFileEditorInput.h"
		},
		
		{
			"file" : "E:/D/MITK/Plugins/org.blueberry.ui.qt/src/berryGeometry.h"
		},
		
		{
			"file" : "E:/D/MITK/Plugins/org.blueberry.ui.qt/src/berryIContextService.h"
		},
		
		{
			"file" : "E:/D/MITK/Plugins/org.blueberry.ui.qt/src/berryIDropTargetListener.h"
		},
		
		{
			"file" : "E:/D/MITK/Plugins/org.blueberry.ui.qt/src/berryIEditorDescriptor.h"
		},
		
		{
			"file" : "E:/D/MITK/Plugins/org.blueberry.ui.qt/src/berryIEditorInput.h"
		},
		
		{
			"file" : "E:/D/MITK/Plugins/org.blueberry.ui.qt/src/berryIEditorMatchingStrategy.h"
		},
		
		{
			"file" : "E:/D/MITK/Plugins/org.blueberry.ui.qt/src/berryIEditorPart.h"
		},
		
		{
			"file" : "E:/D/MITK/Plugins/org.blueberry.ui.qt/src/berryIEditorReference.h"
		},
		
		{
			"file" : "E:/D/MITK/Plugins/org.blueberry.ui.qt/src/berryIEditorRegistry.h"
		},
		
		{
			"file" : "E:/D/MITK/Plugins/org.blueberry.ui.qt/src/berryIEditorSite.h"
		},
		
		{
			"file" : "E:/D/MITK/Plugins/org.blueberry.ui.qt/src/berryIElementFactory.h"
		},
		
		{
			"file" : "E:/D/MITK/Plugins/org.blueberry.ui.qt/src/berryIFileEditorMapping.h"
		},
		
		{
			"file" : "E:/D/MITK/Plugins/org.blueberry.ui.qt/src/berryIFolderLayout.h"
		},
		
		{
			"file" : "E:/D/MITK/Plugins/org.blueberry.ui.qt/src/berryIMemento.h"
		},
		
		{
			"file" : "E:/D/MITK/Plugins/org.blueberry.ui.qt/src/berryINullSelectionListener.h"
		},
		
		{
			"file" : "E:/D/MITK/Plugins/org.blueberry.ui.qt/src/berryIPageLayout.h"
		},
		
		{
			"file" : "E:/D/MITK/Plugins/org.blueberry.ui.qt/src/berryIPartListener.h"
		},
		
		{
			"file" : "E:/D/MITK/Plugins/org.blueberry.ui.qt/src/berryIPageService.h"
		},
		
		{
			"file" : "E:/D/MITK/Plugins/org.blueberry.ui.qt/src/berryIPartService.h"
		},
		
		{
			"file" : "E:/D/MITK/Plugins/org.blueberry.ui.qt/src/berryIPathEditorInput.h"
		},
		
		{
			"file" : "E:/D/MITK/Plugins/org.blueberry.ui.qt/src/berryIPersistable.h"
		},
		
		{
			"file" : "E:/D/MITK/Plugins/org.blueberry.ui.qt/src/berryIPerspectiveDescriptor.h"
		},
		
		{
			"file" : "E:/D/MITK/Plugins/org.blueberry.ui.qt/src/berryIPerspectiveFactory.h"
		},
		
		{
			"file" : "E:/D/MITK/Plugins/org.blueberry.ui.qt/src/berryIPerspectiveListener.h"
		},
		
		{
			"file" : "E:/D/MITK/Plugins/org.blueberry.ui.qt/src/berryIPerspectiveRegistry.h"
		},
		
		{
			"file" : "E:/D/MITK/Plugins/org.blueberry.ui.qt/src/berryIPlaceholderFolderLayout.h"
		},
		
		{
			"file" : "E:/D/MITK/Plugins/org.blueberry.ui.qt/src/berryIPostSelectionProvider.h"
		},
		
		{
			"file" : "E:/D/MITK/Plugins/org.blueberry.ui.qt/src/berryIPreferencePage.h"
		},
		
		{
			"file" : "E:/D/MITK/Plugins/org.blueberry.ui.qt/src/berryIPropertyChangeListener.h"
		},
		
		{
			"file" : "E:/D/MITK/Plugins/org.blueberry.ui.qt/src/berryIQtPreferencePage.h"
		},
		
		{
			"file" : "E:/D/MITK/Plugins/org.blueberry.ui.qt/src/berryIQtStyleManager.h"
		},
		
		{
			"file" : "E:/D/MITK/Plugins/org.blueberry.ui.qt/src/berryIReusableEditor.h"
		},
		
		{
			"file" : "E:/D/MITK/Plugins/org.blueberry.ui.qt/src/berryISaveablePart.h"
		},
		
		{
			"file" : "E:/D/MITK/Plugins/org.blueberry.ui.qt/src/berryISaveablesLifecycleListener.h"
		},
		
		{
			"file" : "E:/D/MITK/Plugins/org.blueberry.ui.qt/src/berryISaveablesSource.h"
		},
		
		{
			"file" : "E:/D/MITK/Plugins/org.blueberry.ui.qt/src/berryISelection.h"
		},
		
		{
			"file" : "E:/D/MITK/Plugins/org.blueberry.ui.qt/src/berryISelectionChangedListener.h"
		},
		
		{
			"file" : "E:/D/MITK/Plugins/org.blueberry.ui.qt/src/berryISelectionListener.h"
		},
		
		{
			"file" : "E:/D/MITK/Plugins/org.blueberry.ui.qt/src/berryISelectionProvider.h"
		},
		
		{
			"file" : "E:/D/MITK/Plugins/org.blueberry.ui.qt/src/berryISelectionService.h"
		},
		
		{
			"file" : "E:/D/MITK/Plugins/org.blueberry.ui.qt/src/berryIShellListener.h"
		},
		
		{
			"file" : "E:/D/MITK/Plugins/org.blueberry.ui.qt/src/berryIShellProvider.h"
		},
		
		{
			"file" : "E:/D/MITK/Plugins/org.blueberry.ui.qt/src/berryISizeProvider.h"
		},
		
		{
			"file" : "E:/D/MITK/Plugins/org.blueberry.ui.qt/src/berryISourceProvider.h"
		},
		
		{
			"file" : "E:/D/MITK/Plugins/org.blueberry.ui.qt/src/berryISourceProviderListener.h"
		},
		
		{
			"file" : "E:/D/MITK/Plugins/org.blueberry.ui.qt/src/berryISources.h"
		},
		
		{
			"file" : "E:/D/MITK/Plugins/org.blueberry.ui.qt/src/berryIStickyViewDescriptor.h"
		},
		
		{
			"file" : "E:/D/MITK/Plugins/org.blueberry.ui.qt/src/berryIStructuredSelection.h"
		},
		
		{
			"file" : "E:/D/MITK/Plugins/org.blueberry.ui.qt/src/berryIViewCategory.h"
		},
		
		{
			"file" : "E:/D/MITK/Plugins/org.blueberry.ui.qt/src/berryIViewDescriptor.h"
		},
		
		{
			"file" : "E:/D/MITK/Plugins/org.blueberry.ui.qt/src/berryIViewLayout.h"
		},
		
		{
			"file" : "E:/D/MITK/Plugins/org.blueberry.ui.qt/src/berryIViewPart.h"
		},
		
		{
			"file" : "E:/D/MITK/Plugins/org.blueberry.ui.qt/src/berryIViewReference.h"
		},
		
		{
			"file" : "E:/D/MITK/Plugins/org.blueberry.ui.qt/src/berryIViewRegistry.h"
		},
		
		{
			"file" : "E:/D/MITK/Plugins/org.blueberry.ui.qt/src/berryIViewSite.h"
		},
		
		{
			"file" : "E:/D/MITK/Plugins/org.blueberry.ui.qt/src/berryIWorkbenchCommandConstants.h"
		},
		
		{
			"file" : "E:/D/MITK/Plugins/org.blueberry.ui.qt/src/berryIWindowListener.h"
		},
		
		{
			"file" : "E:/D/MITK/Plugins/org.blueberry.ui.qt/src/berryIWorkbench.h"
		},
		
		{
			"file" : "E:/D/MITK/Plugins/org.blueberry.ui.qt/src/berryIWorkbenchListener.h"
		},
		
		{
			"file" : "E:/D/MITK/Plugins/org.blueberry.ui.qt/src/berryIWorkbenchPage.h"
		},
		
		{
			"file" : "E:/D/MITK/Plugins/org.blueberry.ui.qt/src/berryIWorkbenchPart.h"
		},
		
		{
			"file" : "E:/D/MITK/Plugins/org.blueberry.ui.qt/src/berryIWorkbenchPartConstants.h"
		},
		
		{
			"file" : "E:/D/MITK/Plugins/org.blueberry.ui.qt/src/berryIWorkbenchPartDescriptor.h"
		},
		
		{
			"file" : "E:/D/MITK/Plugins/org.blueberry.ui.qt/src/berryIWorkbenchPartReference.h"
		},
		
		{
			"file" : "E:/D/MITK/Plugins/org.blueberry.ui.qt/src/berryIWorkbenchPartSite.h"
		},
		
		{
			"file" : "E:/D/MITK/Plugins/org.blueberry.ui.qt/src/berryIWorkbenchSite.h"
		},
		
		{
			"file" : "E:/D/MITK/Plugins/org.blueberry.ui.qt/src/berryIWorkbenchWindow.h"
		},
		
		{
			"file" : "E:/D/MITK/Plugins/org.blueberry.ui.qt/src/berryMenuUtil.h"
		},
		
		{
			"file" : "E:/D/MITK/Plugins/org.blueberry.ui.qt/src/berryPlatformUI.h"
		},
		
		{
			"file" : "E:/D/MITK/Plugins/org.blueberry.ui.qt/src/berryPropertyChangeEvent.h"
		},
		
		{
			"file" : "E:/D/MITK/Plugins/org.blueberry.ui.qt/src/berryQModelIndexObject.h"
		},
		
		{
			"file" : "E:/D/MITK/Plugins/org.blueberry.ui.qt/src/berryQtEditorPart.h"
		},
		
		{
			"file" : "E:/D/MITK/Plugins/org.blueberry.ui.qt/src/berryQtItemSelection.h"
		},
		
		{
			"file" : "E:/D/MITK/Plugins/org.blueberry.ui.qt/src/berryQtIntroPart.h"
		},
		
		{
			"file" : "E:/D/MITK/Plugins/org.blueberry.ui.qt/src/berryQtPreferences.h"
		},
		
		{
			"file" : "E:/D/MITK/Plugins/org.blueberry.ui.qt/src/berryQtSelectionProvider.h"
		},
		
		{
			"file" : "E:/D/MITK/Plugins/org.blueberry.ui.qt/src/berryQtViewPart.h"
		},
		
		{
			"file" : "E:/D/MITK/Plugins/org.blueberry.ui.qt/src/berrySameShellProvider.h"
		},
		
		{
			"file" : "E:/D/MITK/Plugins/org.blueberry.ui.qt/src/berrySaveable.h"
		},
		
		{
			"file" : "E:/D/MITK/Plugins/org.blueberry.ui.qt/src/berrySaveablesLifecycleEvent.h"
		},
		
		{
			"file" : "E:/D/MITK/Plugins/org.blueberry.ui.qt/src/berrySelectionChangedEvent.h"
		},
		
		{
			"file" : "E:/D/MITK/Plugins/org.blueberry.ui.qt/src/berryShell.h"
		},
		
		{
			"file" : "E:/D/MITK/Plugins/org.blueberry.ui.qt/src/berryShellEvent.h"
		},
		
		{
			"file" : "E:/D/MITK/Plugins/org.blueberry.ui.qt/src/berryShowInContext.h"
		},
		
		{
			"file" : "E:/D/MITK/Plugins/org.blueberry.ui.qt/src/berryUIException.h"
		},
		
		{
			"file" : "E:/D/MITK/Plugins/org.blueberry.ui.qt/src/berryViewPart.h"
		},
		
		{
			"file" : "E:/D/MITK/Plugins/org.blueberry.ui.qt/src/berryWindow.h"
		},
		
		{
			"file" : "E:/D/MITK/Plugins/org.blueberry.ui.qt/src/berryWorkbenchActionConstants.h"
		},
		
		{
			"file" : "E:/D/MITK/Plugins/org.blueberry.ui.qt/src/berryWorkbenchPart.h"
		},
		
		{
			"file" : "E:/D/MITK/Plugins/org.blueberry.ui.qt/src/berryWorkbenchPreferenceConstants.h"
		},
		
		{
			"file" : "E:/D/MITK/Plugins/org.blueberry.ui.qt/src/berryXMLMemento.h"
		},
		
		{
			"file" : "E:/D/MITK/Plugins/org.blueberry.ui.qt/src/actions/berryAbstractContributionFactory.h"
		},
		
		{
			"file" : "E:/D/MITK/Plugins/org.blueberry.ui.qt/src/actions/berryCommandContributionItem.h"
		},
		
		{
			"file" : "E:/D/MITK/Plugins/org.blueberry.ui.qt/src/actions/berryCommandContributionItemParameter.h"
		},
		
		{
			"file" : "E:/D/MITK/Plugins/org.blueberry.ui.qt/src/actions/berryContributionItem.h"
		},
		
		{
			"file" : "E:/D/MITK/Plugins/org.blueberry.ui.qt/src/actions/berryContributionItemFactory.h"
		},
		
		{
			"file" : "E:/D/MITK/Plugins/org.blueberry.ui.qt/src/actions/berryContributionManager.h"
		},
		
		{
			"file" : "E:/D/MITK/Plugins/org.blueberry.ui.qt/src/actions/berryGroupMarker.h"
		},
		
		{
			"file" : "E:/D/MITK/Plugins/org.blueberry.ui.qt/src/actions/berryIContributionManagerOverrides.h"
		},
		
		{
			"file" : "E:/D/MITK/Plugins/org.blueberry.ui.qt/src/actions/berryMenuManager.h"
		},
		
		{
			"file" : "E:/D/MITK/Plugins/org.blueberry.ui.qt/src/actions/berryQActionContributionItem.h"
		},
		
		{
			"file" : "E:/D/MITK/Plugins/org.blueberry.ui.qt/src/actions/berryQActionProperties.h"
		},
		
		{
			"file" : "E:/D/MITK/Plugins/org.blueberry.ui.qt/src/actions/berrySeparator.h"
		},
		
		{
			"file" : "E:/D/MITK/Plugins/org.blueberry.ui.qt/src/actions/berrySubContributionItem.h"
		},
		
		{
			"file" : "E:/D/MITK/Plugins/org.blueberry.ui.qt/src/application/berryActionBarAdvisor.h"
		},
		
		{
			"file" : "E:/D/MITK/Plugins/org.blueberry.ui.qt/src/application/berryIActionBarConfigurer.h"
		},
		
		{
			"file" : "E:/D/MITK/Plugins/org.blueberry.ui.qt/src/application/berryIWorkbenchConfigurer.h"
		},
		
		{
			"file" : "E:/D/MITK/Plugins/org.blueberry.ui.qt/src/application/berryIWorkbenchWindowConfigurer.h"
		},
		
		{
			"file" : "E:/D/MITK/Plugins/org.blueberry.ui.qt/src/application/berryWorkbenchAdvisor.h"
		},
		
		{
			"file" : "E:/D/MITK/Plugins/org.blueberry.ui.qt/src/application/berryWorkbenchWindowAdvisor.h"
		},
		
		{
			"file" : "E:/D/MITK/Plugins/org.blueberry.ui.qt/src/commands/berryICommandImageService.h"
		},
		
		{
			"file" : "E:/D/MITK/Plugins/org.blueberry.ui.qt/src/commands/berryICommandService.h"
		},
		
		{
			"file" : "E:/D/MITK/Plugins/org.blueberry.ui.qt/src/commands/berryUIElement.h"
		},
		
		{
			"file" : "E:/D/MITK/Plugins/org.blueberry.ui.qt/src/guitk/berryGuiTkControlEvent.h"
		},
		
		{
			"file" : "E:/D/MITK/Plugins/org.blueberry.ui.qt/src/guitk/berryGuiTkEvent.h"
		},
		
		{
			"file" : "E:/D/MITK/Plugins/org.blueberry.ui.qt/src/guitk/berryGuiTkIControlListener.h"
		},
		
		{
			"file" : "E:/D/MITK/Plugins/org.blueberry.ui.qt/src/guitk/berryGuiTkISelectionListener.h"
		},
		
		{
			"file" : "E:/D/MITK/Plugins/org.blueberry.ui.qt/src/guitk/berryGuiTkSelectionEvent.h"
		},
		
		{
			"file" : "E:/D/MITK/Plugins/org.blueberry.ui.qt/src/handlers/berryHandlerUtil.h"
		},
		
		{
			"file" : "E:/D/MITK/Plugins/org.blueberry.ui.qt/src/handlers/berryIHandlerActivation.h"
		},
		
		{
			"file" : "E:/D/MITK/Plugins/org.blueberry.ui.qt/src/handlers/berryIHandlerService.h"
		},
		
		{
			"file" : "E:/D/MITK/Plugins/org.blueberry.ui.qt/src/handlers/berryRadioState.h"
		},
		
		{
			"file" : "E:/D/MITK/Plugins/org.blueberry.ui.qt/src/handlers/berryRegistryToggleState.h"
		},
		
		{
			"file" : "E:/D/MITK/Plugins/org.blueberry.ui.qt/src/handlers/berryToggleState.h"
		},
		
		{
			"file" : "E:/D/MITK/Plugins/org.blueberry.ui.qt/src/intro/berryIIntroManager.h"
		},
		
		{
			"file" : "E:/D/MITK/Plugins/org.blueberry.ui.qt/src/intro/berryIIntroPart.h"
		},
		
		{
			"file" : "E:/D/MITK/Plugins/org.blueberry.ui.qt/src/intro/berryIIntroSite.h"
		},
		
		{
			"file" : "E:/D/MITK/Plugins/org.blueberry.ui.qt/src/intro/berryIntroPart.h"
		},
		
		{
			"file" : "E:/D/MITK/Plugins/org.blueberry.ui.qt/src/model/berryPerspectiveListModel.h"
		},
		
		{
			"file" : "E:/D/MITK/Plugins/org.blueberry.ui.qt/src/model/berryViewTreeModel.h"
		},
		
		{
			"file" : "E:/D/MITK/Plugins/org.blueberry.ui.qt/src/tweaklets/berryGuiWidgetsTweaklet.h"
		},
		
		{
			"file" : "E:/D/MITK/Plugins/org.blueberry.ui.qt/src/tweaklets/berryWorkbenchPageTweaklet.h"
		},
		
		{
			"file" : "E:/D/MITK/Plugins/org.blueberry.ui.qt/src/tweaklets/berryWorkbenchTweaklet.h"
		},
		
		{
			"file" : "E:/D/MITK/Plugins/org.blueberry.ui.qt/src/presentations/berryIPresentablePart.h"
		},
		
		{
			"file" : "E:/D/MITK/Plugins/org.blueberry.ui.qt/src/presentations/berryIPresentationFactory.h"
		},
		
		{
			"file" : "E:/D/MITK/Plugins/org.blueberry.ui.qt/src/presentations/berryIPresentationSerializer.h"
		},
		
		{
			"file" : "E:/D/MITK/Plugins/org.blueberry.ui.qt/src/presentations/berryIStackPresentationSite.h"
		},
		
		{
			"file" : "E:/D/MITK/Plugins/org.blueberry.ui.qt/src/presentations/berryStackDropResult.h"
		},
		
		{
			"file" : "E:/D/MITK/Plugins/org.blueberry.ui.qt/src/presentations/berryStackPresentation.h"
		},
		
		{
			"file" : "E:/D/MITK/Plugins/org.blueberry.ui.qt/src/services/berryIDisposable.h"
		},
		
		{
			"file" : "E:/D/MITK/Plugins/org.blueberry.ui.qt/src/services/berryIEvaluationService.h"
		},
		
		{
			"file" : "E:/D/MITK/Plugins/org.blueberry.ui.qt/src/services/berryINestable.h"
		},
		
		{
			"file" : "E:/D/MITK/Plugins/org.blueberry.ui.qt/src/services/berryIServiceFactory.h"
		},
		
		{
			"file" : "E:/D/MITK/Plugins/org.blueberry.ui.qt/src/services/berryIServiceLocator.h"
		},
		
		{
			"file" : "E:/D/MITK/Plugins/org.blueberry.ui.qt/src/services/berryIServiceScopes.h"
		},
		
		{
			"file" : "E:/D/MITK/Plugins/org.blueberry.ui.qt/src/services/berryIServiceWithSources.h"
		},
		
		{
			"file" : "E:/D/MITK/Plugins/org.blueberry.ui.qt/src/services/berryISourceProviderService.h"
		},
		
		{
			"file" : "E:/D/MITK/Plugins/org.blueberry.ui.qt/src/testing/berryTestableObject.h"
		},
		
		{
			"file" : "E:/D/MITK/Plugins/org.blueberry.ui.qt/src/util/berryISafeRunnableRunner.h"
		},
		
		{
			"file" : "E:/D/MITK/Plugins/org.blueberry.ui.qt/src/util/berrySafeRunnable.h"
		},
		
		{
			"file" : "E:/D/MITK/Plugins/org.blueberry.ui.qt/src/application/berryQtWorkbenchAdvisor.h"
		},
		
		{
			"file" : "E:/D/MITK/Plugins/org.blueberry.ui.qt/src/internal/defaultpresentation/berryEmptyTabFolder.h"
		},
		
		{
			"file" : "E:/D/MITK/Plugins/org.blueberry.ui.qt/src/internal/defaultpresentation/berryEmptyTabItem.h"
		},
		
		{
			"file" : "E:/D/MITK/Plugins/org.blueberry.ui.qt/src/internal/defaultpresentation/berryNativeTabFolder.h"
		},
		
		{
			"file" : "E:/D/MITK/Plugins/org.blueberry.ui.qt/src/internal/defaultpresentation/berryNativeTabItem.h"
		},
		
		{
			"file" : "E:/D/MITK/Plugins/org.blueberry.ui.qt/src/internal/defaultpresentation/berryQCTabBar.h"
		},
		
		{
			"file" : "E:/D/MITK/Plugins/org.blueberry.ui.qt/src/internal/defaultpresentation/berryQtWorkbenchPresentationFactory.h"
		},
		
		{
			"file" : "E:/D/MITK/Plugins/org.blueberry.ui.qt/src/internal/dialogs/berryPerspectivesPreferencePage.h"
		},
		
		{
			"file" : "E:/D/MITK/Plugins/org.blueberry.ui.qt/src/internal/dialogs/berrySavePerspectiveDialog.h"
		},
		
		{
			"file" : "E:/D/MITK/Plugins/org.blueberry.ui.qt/src/internal/handlers/berryCloseAllPerspectivesHandler.h"
		},
		
		{
			"file" : "E:/D/MITK/Plugins/org.blueberry.ui.qt/src/internal/handlers/berryClosePerspectiveHandler.h"
		},
		
		{
			"file" : "E:/D/MITK/Plugins/org.blueberry.ui.qt/src/internal/handlers/berryDynamicHelpHandler.h"
		},
		
		{
			"file" : "E:/D/MITK/Plugins/org.blueberry.ui.qt/src/internal/handlers/berryHelpContentsHandler.h"
		},
		
		{
			"file" : "E:/D/MITK/Plugins/org.blueberry.ui.qt/src/internal/handlers/berryIntroHandler.h"
		},
		
		{
			"file" : "E:/D/MITK/Plugins/org.blueberry.ui.qt/src/internal/handlers/berryNewEditorHandler.h"
		},
		
		{
			"file" : "E:/D/MITK/Plugins/org.blueberry.ui.qt/src/internal/handlers/berryOpenInNewWindowHandler.h"
		},
		
		{
			"file" : "E:/D/MITK/Plugins/org.blueberry.ui.qt/src/internal/handlers/berryQuitHandler.h"
		},
		
		{
			"file" : "E:/D/MITK/Plugins/org.blueberry.ui.qt/src/internal/handlers/berryResetPerspectiveHandler.h"
		},
		
		{
			"file" : "E:/D/MITK/Plugins/org.blueberry.ui.qt/src/internal/handlers/berrySavePerspectiveHandler.h"
		},
		
		{
			"file" : "E:/D/MITK/Plugins/org.blueberry.ui.qt/src/internal/handlers/berryShowPerspectiveHandler.h"
		},
		
		{
			"file" : "E:/D/MITK/Plugins/org.blueberry.ui.qt/src/internal/handlers/berryShowViewHandler.h"
		},
		
		{
			"file" : "E:/D/MITK/Plugins/org.blueberry.ui.qt/src/internal/util/berryAbstractTabFolder.h"
		},
		
		{
			"file" : "E:/D/MITK/Plugins/org.blueberry.ui.qt/src/internal/util/berryAbstractTabItem.h"
		},
		
		{
			"file" : "E:/D/MITK/Plugins/org.blueberry.ui.qt/src/internal/util/berryIPresentablePartList.h"
		},
		
		{
			"file" : "E:/D/MITK/Plugins/org.blueberry.ui.qt/src/internal/util/berryLeftToRightTabOrder.h"
		},
		
		{
			"file" : "E:/D/MITK/Plugins/org.blueberry.ui.qt/src/internal/util/berryPartInfo.h"
		},
		
		{
			"file" : "E:/D/MITK/Plugins/org.blueberry.ui.qt/src/internal/util/berryPresentablePartFolder.h"
		},
		
		{
			"file" : "E:/D/MITK/Plugins/org.blueberry.ui.qt/src/internal/util/berryReplaceDragHandler.h"
		},
		
		{
			"file" : "E:/D/MITK/Plugins/org.blueberry.ui.qt/src/internal/util/berryTabbedStackPresentation.h"
		},
		
		{
			"file" : "E:/D/MITK/Plugins/org.blueberry.ui.qt/src/internal/util/berryTabDragHandler.h"
		},
		
		{
			"file" : "E:/D/MITK/Plugins/org.blueberry.ui.qt/src/internal/util/berryTabFolderEvent.h"
		},
		
		{
			"file" : "E:/D/MITK/Plugins/org.blueberry.ui.qt/src/internal/util/berryTabOrder.h"
		},
		
		{
			"file" : "E:/D/MITK/Plugins/org.blueberry.ui.qt/src/internal/intro/berryEditorIntroAdapterPart.h"
		},
		
		{
			"file" : "E:/D/MITK/Plugins/org.blueberry.ui.qt/src/internal/intro/berryIIntroDescriptor.h"
		},
		
		{
			"file" : "E:/D/MITK/Plugins/org.blueberry.ui.qt/src/internal/intro/berryIIntroRegistry.h"
		},
		
		{
			"file" : "E:/D/MITK/Plugins/org.blueberry.ui.qt/src/internal/intro/berryIntroConstants.h"
		},
		
		{
			"file" : "E:/D/MITK/Plugins/org.blueberry.ui.qt/src/internal/intro/berryIntroDescriptor.h"
		},
		
		{
			"file" : "E:/D/MITK/Plugins/org.blueberry.ui.qt/src/internal/intro/berryIntroPartAdapterSite.h"
		},
		
		{
			"file" : "E:/D/MITK/Plugins/org.blueberry.ui.qt/src/internal/intro/berryIntroRegistry.h"
		},
		
		{
			"file" : "E:/D/MITK/Plugins/org.blueberry.ui.qt/src/internal/intro/berryViewIntroAdapterPart.h"
		},
		
		{
			"file" : "E:/D/MITK/Plugins/org.blueberry.ui.qt/src/internal/intro/berryWorkbenchIntroManager.h"
		},
		
		{
			"file" : "E:/D/MITK/Plugins/org.blueberry.ui.qt/src/internal/berryAbstractGroupMarker.h"
		},
		
		{
			"file" : "E:/D/MITK/Plugins/org.blueberry.ui.qt/src/internal/berryAbstractMenuAdditionCacheEntry.h"
		},
		
		{
			"file" : "E:/D/MITK/Plugins/org.blueberry.ui.qt/src/internal/berryAbstractPartSelectionTracker.h"
		},
		
		{
			"file" : "E:/D/MITK/Plugins/org.blueberry.ui.qt/src/internal/berryAbstractSelectionService.h"
		},
		
		{
			"file" : "E:/D/MITK/Plugins/org.blueberry.ui.qt/src/internal/berryActivePartExpression.h"
		},
		
		{
			"file" : "E:/D/MITK/Plugins/org.blueberry.ui.qt/src/internal/berryAlwaysEnabledExpression.h"
		},
		
		{
			"file" : "E:/D/MITK/Plugins/org.blueberry.ui.qt/src/internal/berryAndExpression.h"
		},
		
		{
			"file" : "E:/D/MITK/Plugins/org.blueberry.ui.qt/src/internal/berryBundleUtility.h"
		},
		
		{
			"file" : "E:/D/MITK/Plugins/org.blueberry.ui.qt/src/internal/berryChangeToPerspectiveMenu.h"
		},
		
		{
			"file" : "E:/D/MITK/Plugins/org.blueberry.ui.qt/src/internal/berryCommandParameter.h"
		},
		
		{
			"file" : "E:/D/MITK/Plugins/org.blueberry.ui.qt/src/internal/berryCommandPersistence.h"
		},
		
		{
			"file" : "E:/D/MITK/Plugins/org.blueberry.ui.qt/src/internal/berryCommandService.h"
		},
		
		{
			"file" : "E:/D/MITK/Plugins/org.blueberry.ui.qt/src/internal/berryCommandServiceFactory.h"
		},
		
		{
			"file" : "E:/D/MITK/Plugins/org.blueberry.ui.qt/src/internal/berryCommandStateProxy.h"
		},
		
		{
			"file" : "E:/D/MITK/Plugins/org.blueberry.ui.qt/src/internal/berryCompositeExpression.h"
		},
		
		{
			"file" : "E:/D/MITK/Plugins/org.blueberry.ui.qt/src/internal/berryContainerPlaceholder.h"
		},
		
		{
			"file" : "E:/D/MITK/Plugins/org.blueberry.ui.qt/src/internal/berryContributionRoot.h"
		},
		
		{
			"file" : "E:/D/MITK/Plugins/org.blueberry.ui.qt/src/internal/berryDetachedPlaceHolder.h"
		},
		
		{
			"file" : "E:/D/MITK/Plugins/org.blueberry.ui.qt/src/internal/berryDefaultSaveable.h"
		},
		
		{
			"file" : "E:/D/MITK/Plugins/org.blueberry.ui.qt/src/internal/berryDefaultStackPresentationSite.h"
		},
		
		{
			"file" : "E:/D/MITK/Plugins/org.blueberry.ui.qt/src/internal/berryDetachedWindow.h"
		},
		
		{
			"file" : "E:/D/MITK/Plugins/org.blueberry.ui.qt/src/internal/berryDirtyPerspectiveMarker.h"
		},
		
		{
			"file" : "E:/D/MITK/Plugins/org.blueberry.ui.qt/src/internal/berryDragUtil.h"
		},
		
		{
			"file" : "E:/D/MITK/Plugins/org.blueberry.ui.qt/src/internal/berryEditorAreaHelper.h"
		},
		
		{
			"file" : "E:/D/MITK/Plugins/org.blueberry.ui.qt/src/internal/berryEditorDescriptor.h"
		},
		
		{
			"file" : "E:/D/MITK/Plugins/org.blueberry.ui.qt/src/internal/berryEditorHistory.h"
		},
		
		{
			"file" : "E:/D/MITK/Plugins/org.blueberry.ui.qt/src/internal/berryEditorHistoryItem.h"
		},
		
		{
			"file" : "E:/D/MITK/Plugins/org.blueberry.ui.qt/src/internal/berryEditorManager.h"
		},
		
		{
			"file" : "E:/D/MITK/Plugins/org.blueberry.ui.qt/src/internal/berryEditorReference.h"
		},
		
		{
			"file" : "E:/D/MITK/Plugins/org.blueberry.ui.qt/src/internal/berryEditorRegistry.h"
		},
		
		{
			"file" : "E:/D/MITK/Plugins/org.blueberry.ui.qt/src/internal/berryEditorRegistryReader.h"
		},
		
		{
			"file" : "E:/D/MITK/Plugins/org.blueberry.ui.qt/src/internal/berryEditorSashContainer.h"
		},
		
		{
			"file" : "E:/D/MITK/Plugins/org.blueberry.ui.qt/src/internal/berryEditorSite.h"
		},
		
		{
			"file" : "E:/D/MITK/Plugins/org.blueberry.ui.qt/src/internal/berryElementReference.h"
		},
		
		{
			"file" : "E:/D/MITK/Plugins/org.blueberry.ui.qt/src/internal/berryErrorViewPart.h"
		},
		
		{
			"file" : "E:/D/MITK/Plugins/org.blueberry.ui.qt/src/internal/berryEvaluationAuthority.h"
		},
		
		{
			"file" : "E:/D/MITK/Plugins/org.blueberry.ui.qt/src/internal/berryEvaluationReference.h"
		},
		
		{
			"file" : "E:/D/MITK/Plugins/org.blueberry.ui.qt/src/internal/berryEvaluationResultCache.h"
		},
		
		{
			"file" : "E:/D/MITK/Plugins/org.blueberry.ui.qt/src/internal/berryEvaluationService.h"
		},
		
		{
			"file" : "E:/D/MITK/Plugins/org.blueberry.ui.qt/src/internal/berryExpressionAuthority.h"
		},
		
		{
			"file" : "E:/D/MITK/Plugins/org.blueberry.ui.qt/src/internal/berryFileEditorMapping.h"
		},
		
		{
			"file" : "E:/D/MITK/Plugins/org.blueberry.ui.qt/src/internal/berryFolderLayout.h"
		},
		
		{
			"file" : "E:/D/MITK/Plugins/org.blueberry.ui.qt/src/internal/berryHandlerActivation.h"
		},
		
		{
			"file" : "E:/D/MITK/Plugins/org.blueberry.ui.qt/src/internal/berryHandlerAuthority.h"
		},
		
		{
			"file" : "E:/D/MITK/Plugins/org.blueberry.ui.qt/src/internal/berryHandlerPersistence.h"
		},
		
		{
			"file" : "E:/D/MITK/Plugins/org.blueberry.ui.qt/src/internal/berryHandlerProxy.h"
		},
		
		{
			"file" : "E:/D/MITK/Plugins/org.blueberry.ui.qt/src/internal/berryHandlerService.h"
		},
		
		{
			"file" : "E:/D/MITK/Plugins/org.blueberry.ui.qt/src/internal/berryHandlerServiceFactory.h"
		},
		
		{
			"file" : "E:/D/MITK/Plugins/org.blueberry.ui.qt/src/internal/berryIDragOverListener.h"
		},
		
		{
			"file" : "E:/D/MITK/Plugins/org.blueberry.ui.qt/src/internal/berryIDropTarget.h"
		},
		
		{
			"file" : "E:/D/MITK/Plugins/org.blueberry.ui.qt/src/internal/berryIEvaluationResultCache.h"
		},
		
		{
			"file" : "E:/D/MITK/Plugins/org.blueberry.ui.qt/src/internal/berryILayoutContainer.h"
		},
		
		{
			"file" : "E:/D/MITK/Plugins/org.blueberry.ui.qt/src/internal/berryIServiceLocatorCreator.h"
		},
		
		{
			"file" : "E:/D/MITK/Plugins/org.blueberry.ui.qt/src/internal/berryIStickyViewManager.h"
		},
		
		{
			"file" : "E:/D/MITK/Plugins/org.blueberry.ui.qt/src/internal/berryIWorkbenchLocationService.h"
		},
		
		{
			"file" : "E:/D/MITK/Plugins/org.blueberry.ui.qt/src/internal/berryKeywordRegistry.h"
		},
		
		{
			"file" : "E:/D/MITK/Plugins/org.blueberry.ui.qt/src/internal/berryLayoutHelper.h"
		},
		
		{
			"file" : "E:/D/MITK/Plugins/org.blueberry.ui.qt/src/internal/berryLayoutPart.h"
		},
		
		{
			"file" : "E:/D/MITK/Plugins/org.blueberry.ui.qt/src/internal/berryLayoutPartSash.h"
		},
		
		{
			"file" : "E:/D/MITK/Plugins/org.blueberry.ui.qt/src/internal/berryLayoutTree.h"
		},
		
		{
			"file" : "E:/D/MITK/Plugins/org.blueberry.ui.qt/src/internal/berryLayoutTreeNode.h"
		},
		
		{
			"file" : "E:/D/MITK/Plugins/org.blueberry.ui.qt/src/internal/berryMenuServiceFactory.h"
		},
		
		{
			"file" : "E:/D/MITK/Plugins/org.blueberry.ui.qt/src/internal/berryNestableHandlerService.h"
		},
		
		{
			"file" : "E:/D/MITK/Plugins/org.blueberry.ui.qt/src/internal/berryNullEditorInput.h"
		},
		
		{
			"file" : "E:/D/MITK/Plugins/org.blueberry.ui.qt/src/internal/berryOpenPerspectivePropertyTester.h"
		},
		
		{
			"file" : "E:/D/MITK/Plugins/org.blueberry.ui.qt/src/internal/berryPageLayout.h"
		},
		
		{
			"file" : "E:/D/MITK/Plugins/org.blueberry.ui.qt/src/internal/berryPagePartSelectionTracker.h"
		},
		
		{
			"file" : "E:/D/MITK/Plugins/org.blueberry.ui.qt/src/internal/berryPageSelectionService.h"
		},
		
		{
			"file" : "E:/D/MITK/Plugins/org.blueberry.ui.qt/src/internal/berryParameterValueConverterProxy.h"
		},
		
		{
			"file" : "E:/D/MITK/Plugins/org.blueberry.ui.qt/src/internal/berryPartList.h"
		},
		
		{
			"file" : "E:/D/MITK/Plugins/org.blueberry.ui.qt/src/internal/berryPartPane.h"
		},
		
		{
			"file" : "E:/D/MITK/Plugins/org.blueberry.ui.qt/src/internal/berryPartPlaceholder.h"
		},
		
		{
			"file" : "E:/D/MITK/Plugins/org.blueberry.ui.qt/src/internal/berryPartSashContainer.h"
		},
		
		{
			"file" : "E:/D/MITK/Plugins/org.blueberry.ui.qt/src/internal/berryPartService.h"
		},
		
		{
			"file" : "E:/D/MITK/Plugins/org.blueberry.ui.qt/src/internal/berryPartSite.h"
		},
		
		{
			"file" : "E:/D/MITK/Plugins/org.blueberry.ui.qt/src/internal/berryPartStack.h"
		},
		
		{
			"file" : "E:/D/MITK/Plugins/org.blueberry.ui.qt/src/internal/berryPartTester.h"
		},
		
		{
			"file" : "E:/D/MITK/Plugins/org.blueberry.ui.qt/src/internal/berryPersistentState.h"
		},
		
		{
			"file" : "E:/D/MITK/Plugins/org.blueberry.ui.qt/src/internal/berryPerspective.h"
		},
		
		{
			"file" : "E:/D/MITK/Plugins/org.blueberry.ui.qt/src/internal/berryPerspectiveDescriptor.h"
		},
		
		{
			"file" : "E:/D/MITK/Plugins/org.blueberry.ui.qt/src/internal/berryPerspectiveExtensionReader.h"
		},
		
		{
			"file" : "E:/D/MITK/Plugins/org.blueberry.ui.qt/src/internal/berryPerspectiveHelper.h"
		},
		
		{
			"file" : "E:/D/MITK/Plugins/org.blueberry.ui.qt/src/internal/berryPerspectiveParameterValues.h"
		},
		
		{
			"file" : "E:/D/MITK/Plugins/org.blueberry.ui.qt/src/internal/berryPerspectiveRegistry.h"
		},
		
		{
			"file" : "E:/D/MITK/Plugins/org.blueberry.ui.qt/src/internal/berryPerspectiveRegistryReader.h"
		},
		
		{
			"file" : "E:/D/MITK/Plugins/org.blueberry.ui.qt/src/internal/berryPlaceholderFolderLayout.h"
		},
		
		{
			"file" : "E:/D/MITK/Plugins/org.blueberry.ui.qt/src/internal/berryPolicy.h"
		},
		
		{
			"file" : "E:/D/MITK/Plugins/org.blueberry.ui.qt/src/internal/berryPreferenceConstants.h"
		},
		
		{
			"file" : "E:/D/MITK/Plugins/org.blueberry.ui.qt/src/internal/berryPreferencePageParameterValues.h"
		},
		
		{
			"file" : "E:/D/MITK/Plugins/org.blueberry.ui.qt/src/internal/berryPresentablePart.h"
		},
		
		{
			"file" : "E:/D/MITK/Plugins/org.blueberry.ui.qt/src/internal/berryPresentationFactoryUtil.h"
		},
		
		{
			"file" : "E:/D/MITK/Plugins/org.blueberry.ui.qt/src/internal/berryPresentationSerializer.h"
		},
		
		{
			"file" : "E:/D/MITK/Plugins/org.blueberry.ui.qt/src/internal/berryQtControlWidget.h"
		},
		
		{
			"file" : "E:/D/MITK/Plugins/org.blueberry.ui.qt/src/internal/berryQtDnDControlWidget.h"
		},
		
		{
			"file" : "E:/D/MITK/Plugins/org.blueberry.ui.qt/src/internal/berryQtDisplay.h"
		},
		
		{
			"file" : "E:/D/MITK/Plugins/org.blueberry.ui.qt/src/internal/berryQtGlobalEventFilter.h"
		},
		
		{
			"file" : "E:/D/MITK/Plugins/org.blueberry.ui.qt/src/internal/berryQtMainWindowControl.h"
		},
		
		{
			"file" : "E:/D/MITK/Plugins/org.blueberry.ui.qt/src/internal/berryQtOpenPerspectiveAction.h"
		},
		
		{
			"file" : "E:/D/MITK/Plugins/org.blueberry.ui.qt/src/internal/berryQtPerspectiveSwitcher.h"
		},
		
		{
			"file" : "E:/D/MITK/Plugins/org.blueberry.ui.qt/src/internal/berryQtSash.h"
		},
		
		{
			"file" : "E:/D/MITK/Plugins/org.blueberry.ui.qt/src/internal/berryQtShell.h"
		},
		
		{
			"file" : "E:/D/MITK/Plugins/org.blueberry.ui.qt/src/internal/berryQtShowPerspectiveDialog.h"
		},
		
		{
			"file" : "E:/D/MITK/Plugins/org.blueberry.ui.qt/src/internal/berryQtShowViewAction.h"
		},
		
		{
			"file" : "E:/D/MITK/Plugins/org.blueberry.ui.qt/src/internal/berryQtShowViewDialog.h"
		},
		
		{
			"file" : "E:/D/MITK/Plugins/org.blueberry.ui.qt/src/internal/berryQtStyleManager.h"
		},
		
		{
			"file" : "E:/D/MITK/Plugins/org.blueberry.ui.qt/src/internal/berryQtStylePreferencePage.h"
		},
		
		{
			"file" : "E:/D/MITK/Plugins/org.blueberry.ui.qt/src/internal/berryQtTracker.h"
		},
		
		{
			"file" : "E:/D/MITK/Plugins/org.blueberry.ui.qt/src/internal/berryQtWidgetController.h"
		},
		
		{
			"file" : "E:/D/MITK/Plugins/org.blueberry.ui.qt/src/internal/berryQtWidgetsTweaklet.h"
		},
		
		{
			"file" : "E:/D/MITK/Plugins/org.blueberry.ui.qt/src/internal/berryQtWidgetsTweakletImpl.h"
		},
		
		{
			"file" : "E:/D/MITK/Plugins/org.blueberry.ui.qt/src/internal/berryQtWorkbenchPageTweaklet.h"
		},
		
		{
			"file" : "E:/D/MITK/Plugins/org.blueberry.ui.qt/src/internal/berryQtWorkbenchTweaklet.h"
		},
		
		{
			"file" : "E:/D/MITK/Plugins/org.blueberry.ui.qt/src/internal/berryRegistryPersistence.h"
		},
		
		{
			"file" : "E:/D/MITK/Plugins/org.blueberry.ui.qt/src/internal/berryRegistryReader.h"
		},
		
		{
			"file" : "E:/D/MITK/Plugins/org.blueberry.ui.qt/src/internal/berryReopenEditorMenu.h"
		},
		
		{
			"file" : "E:/D/MITK/Plugins/org.blueberry.ui.qt/src/internal/berrySaveablesList.h"
		},
		
		{
			"file" : "E:/D/MITK/Plugins/org.blueberry.ui.qt/src/internal/berryShowViewMenu.h"
		},
		
		{
			"file" : "E:/D/MITK/Plugins/org.blueberry.ui.qt/src/internal/berryServiceLocator.h"
		},
		
		{
			"file" : "E:/D/MITK/Plugins/org.blueberry.ui.qt/src/internal/berryServiceLocatorCreator.h"
		},
		
		{
			"file" : "E:/D/MITK/Plugins/org.blueberry.ui.qt/src/internal/berryShellPool.h"
		},
		
		{
			"file" : "E:/D/MITK/Plugins/org.blueberry.ui.qt/src/internal/berrySlaveCommandService.h"
		},
		
		{
			"file" : "E:/D/MITK/Plugins/org.blueberry.ui.qt/src/internal/berrySlaveHandlerService.h"
		},
		
		{
			"file" : "E:/D/MITK/Plugins/org.blueberry.ui.qt/src/internal/berrySlaveMenuService.h"
		},
		
		{
			"file" : "E:/D/MITK/Plugins/org.blueberry.ui.qt/src/internal/berrySourceProviderService.h"
		},
		
		{
			"file" : "E:/D/MITK/Plugins/org.blueberry.ui.qt/src/internal/berrySourcePriorityNameMapping.h"
		},
		
		{
			"file" : "E:/D/MITK/Plugins/org.blueberry.ui.qt/src/internal/berryStatusUtil.h"
		},
		
		{
			"file" : "E:/D/MITK/Plugins/org.blueberry.ui.qt/src/internal/berryStickyViewDescriptor.h"
		},
		
		{
			"file" : "E:/D/MITK/Plugins/org.blueberry.ui.qt/src/internal/berryStickyViewManager.h"
		},
		
		{
			"file" : "E:/D/MITK/Plugins/org.blueberry.ui.qt/src/internal/berrySwitchToWindowMenu.h"
		},
		
		{
			"file" : "E:/D/MITK/Plugins/org.blueberry.ui.qt/src/internal/berryTweaklets.h"
		},
		
		{
			"file" : "E:/D/MITK/Plugins/org.blueberry.ui.qt/src/internal/berryUIExtensionTracker.h"
		},
		
		{
			"file" : "E:/D/MITK/Plugins/org.blueberry.ui.qt/src/internal/berryUtil.h"
		},
		
		{
			"file" : "E:/D/MITK/Plugins/org.blueberry.ui.qt/src/internal/berryViewDescriptor.h"
		},
		
		{
			"file" : "E:/D/MITK/Plugins/org.blueberry.ui.qt/src/internal/berryViewFactory.h"
		},
		
		{
			"file" : "E:/D/MITK/Plugins/org.blueberry.ui.qt/src/internal/berryViewLayout.h"
		},
		
		{
			"file" : "E:/D/MITK/Plugins/org.blueberry.ui.qt/src/internal/berryViewReference.h"
		},
		
		{
			"file" : "E:/D/MITK/Plugins/org.blueberry.ui.qt/src/internal/berryViewRegistry.h"
		},
		
		{
			"file" : "E:/D/MITK/Plugins/org.blueberry.ui.qt/src/internal/berryViewRegistryReader.h"
		},
		
		{
			"file" : "E:/D/MITK/Plugins/org.blueberry.ui.qt/src/internal/berryViewSashContainer.h"
		},
		
		{
			"file" : "E:/D/MITK/Plugins/org.blueberry.ui.qt/src/internal/berryViewSite.h"
		},
		
		{
			"file" : "E:/D/MITK/Plugins/org.blueberry.ui.qt/src/internal/berryWorkbenchPage.h"
		},
		
		{
			"file" : "E:/D/MITK/Plugins/org.blueberry.ui.qt/src/internal/berryWindowManager.h"
		},
		
		{
			"file" : "E:/D/MITK/Plugins/org.blueberry.ui.qt/src/internal/berryWindowPartSelectionTracker.h"
		},
		
		{
			"file" : "E:/D/MITK/Plugins/org.blueberry.ui.qt/src/internal/berryWindowSelectionService.h"
		},
		
		{
			"file" : "E:/D/MITK/Plugins/org.blueberry.ui.qt/src/internal/berryWorkbench.h"
		},
		
		{
			"file" : "E:/D/MITK/Plugins/org.blueberry.ui.qt/src/internal/berryWorkbenchConfigurer.h"
		},
		
		{
			"file" : "E:/D/MITK/Plugins/org.blueberry.ui.qt/src/internal/berryWorkbenchConstants.h"
		},
		
		{
			"file" : "E:/D/MITK/Plugins/org.blueberry.ui.qt/src/internal/berryWorkbenchLocationService.h"
		},
		
		{
			"file" : "E:/D/MITK/Plugins/org.blueberry.ui.qt/src/internal/berryWorkbenchMenuService.h"
		},
		
		{
			"file" : "E:/D/MITK/Plugins/org.blueberry.ui.qt/src/internal/berryWorkbenchPagePartList.h"
		},
		
		{
			"file" : "E:/D/MITK/Plugins/org.blueberry.ui.qt/src/internal/berryWorkbenchPartReference.h"
		},
		
		{
			"file" : "E:/D/MITK/Plugins/org.blueberry.ui.qt/src/internal/berryWorkbenchPlugin.h"
		},
		
		{
			"file" : "E:/D/MITK/Plugins/org.blueberry.ui.qt/src/internal/berryWorkbenchRegistryConstants.h"
		},
		
		{
			"file" : "E:/D/MITK/Plugins/org.blueberry.ui.qt/src/internal/berryWorkbenchServiceRegistry.h"
		},
		
		{
			"file" : "E:/D/MITK/Plugins/org.blueberry.ui.qt/src/internal/berryWorkbenchSourceProvider.h"
		},
		
		{
			"file" : "E:/D/MITK/Plugins/org.blueberry.ui.qt/src/internal/berryWorkbenchTestable.h"
		},
		
		{
			"file" : "E:/D/MITK/Plugins/org.blueberry.ui.qt/src/internal/berryWorkbenchWindow.h"
		},
		
		{
			"file" : "E:/D/MITK/Plugins/org.blueberry.ui.qt/src/internal/berryWorkbenchWindowConfigurer.h"
		},
		
		{
			"file" : "E:/D/MITK/Plugins/org.blueberry.ui.qt/src/internal/berryWorkbenchWindowExpression.h"
		},
		
		{
			"file" : "E:/D/MITK/Plugins/org.blueberry.ui.qt/src/internal/berryWWinActionBars.h"
		},
		
		{
			"file" : "E:/D/MITK/Plugins/org.blueberry.ui.qt/src/internal/berryWWinPartService.h"
		},
		
		{
			"file" : "E:/D/MITK-superbuild/MITK-build/Plugins/org.blueberry.ui.qt/src/moc_berryAbstractUICTKPlugin.cpp"
		},
		
		{
			"file" : "E:/D/MITK-superbuild/MITK-build/Plugins/org.blueberry.ui.qt/src/moc_berryEditorPart.cpp"
		},
		
		{
			"file" : "E:/D/MITK-superbuild/MITK-build/Plugins/org.blueberry.ui.qt/src/moc_berryExtensionFactory.cpp"
		},
		
		{
			"file" : "E:/D/MITK-superbuild/MITK-build/Plugins/org.blueberry.ui.qt/src/moc_berryQtSelectionProvider.cpp"
		},
		
		{
			"file" : "E:/D/MITK-superbuild/MITK-build/Plugins/org.blueberry.ui.qt/src/moc_berryViewPart.cpp"
		},
		
		{
			"file" : "E:/D/MITK-superbuild/MITK-build/Plugins/org.blueberry.ui.qt/src/moc_berryWorkbenchPart.cpp"
		},
		
		{
			"file" : "E:/D/MITK-superbuild/MITK-build/Plugins/org.blueberry.ui.qt/src/actions/moc_berryCommandContributionItem.cpp"
		},
		
		{
			"file" : "E:/D/MITK-superbuild/MITK-build/Plugins/org.blueberry.ui.qt/src/actions/moc_berryMenuManager.cpp"
		},
		
		{
			"file" : "E:/D/MITK-superbuild/MITK-build/Plugins/org.blueberry.ui.qt/src/intro/moc_berryIntroPart.cpp"
		},
		
		{
			"file" : "E:/D/MITK-superbuild/MITK-build/Plugins/org.blueberry.ui.qt/src/model/moc_berryPerspectiveListModel.cpp"
		},
		
		{
			"file" : "E:/D/MITK-superbuild/MITK-build/Plugins/org.blueberry.ui.qt/src/model/moc_berryViewTreeModel.cpp"
		},
		
		{
			"file" : "E:/D/MITK-superbuild/MITK-build/Plugins/org.blueberry.ui.qt/src/internal/moc_berryChangeToPerspectiveMenu.cpp"
		},
		
		{
			"file" : "E:/D/MITK-superbuild/MITK-build/Plugins/org.blueberry.ui.qt/src/internal/moc_berryCommandServiceFactory.cpp"
		},
		
		{
			"file" : "E:/D/MITK-superbuild/MITK-build/Plugins/org.blueberry.ui.qt/src/internal/moc_berryHandlerServiceFactory.cpp"
		},
		
		{
			"file" : "E:/D/MITK-superbuild/MITK-build/Plugins/org.blueberry.ui.qt/src/internal/moc_berryMenuServiceFactory.cpp"
		},
		
		{
			"file" : "E:/D/MITK-superbuild/MITK-build/Plugins/org.blueberry.ui.qt/src/internal/moc_berryOpenPerspectivePropertyTester.cpp"
		},
		
		{
			"file" : "E:/D/MITK-superbuild/MITK-build/Plugins/org.blueberry.ui.qt/src/internal/moc_berryPerspectiveParameterValues.cpp"
		},
		
		{
			"file" : "E:/D/MITK-superbuild/MITK-build/Plugins/org.blueberry.ui.qt/src/internal/moc_berryPreferencePageParameterValues.cpp"
		},
		
		{
			"file" : "E:/D/MITK-superbuild/MITK-build/Plugins/org.blueberry.ui.qt/src/internal/moc_berryQtDisplay.cpp"
		},
		
		{
			"file" : "E:/D/MITK-superbuild/MITK-build/Plugins/org.blueberry.ui.qt/src/internal/moc_berryQtGlobalEventFilter.cpp"
		},
		
		{
			"file" : "E:/D/MITK-superbuild/MITK-build/Plugins/org.blueberry.ui.qt/src/internal/moc_berryQtMainWindowControl.cpp"
		},
		
		{
			"file" : "E:/D/MITK-superbuild/MITK-build/Plugins/org.blueberry.ui.qt/src/internal/moc_berryQtOpenPerspectiveAction.cpp"
		},
		
		{
			"file" : "E:/D/MITK-superbuild/MITK-build/Plugins/org.blueberry.ui.qt/src/internal/moc_berryQtPerspectiveSwitcher.cpp"
		},
		
		{
			"file" : "E:/D/MITK-superbuild/MITK-build/Plugins/org.blueberry.ui.qt/src/internal/moc_berryQtSash.cpp"
		},
		
		{
			"file" : "E:/D/MITK-superbuild/MITK-build/Plugins/org.blueberry.ui.qt/src/internal/moc_berryQtShowPerspectiveDialog.cpp"
		},
		
		{
			"file" : "E:/D/MITK-superbuild/MITK-build/Plugins/org.blueberry.ui.qt/src/internal/moc_berryQtShowViewAction.cpp"
		},
		
		{
			"file" : "E:/D/MITK-superbuild/MITK-build/Plugins/org.blueberry.ui.qt/src/internal/moc_berryQtShowViewDialog.cpp"
		},
		
		{
			"file" : "E:/D/MITK-superbuild/MITK-build/Plugins/org.blueberry.ui.qt/src/internal/moc_berryQtStyleManager.cpp"
		},
		
		{
			"file" : "E:/D/MITK-superbuild/MITK-build/Plugins/org.blueberry.ui.qt/src/internal/moc_berryQtStylePreferencePage.cpp"
		},
		
		{
			"file" : "E:/D/MITK-superbuild/MITK-build/Plugins/org.blueberry.ui.qt/src/internal/moc_berryQtTracker.cpp"
		},
		
		{
			"file" : "E:/D/MITK-superbuild/MITK-build/Plugins/org.blueberry.ui.qt/src/internal/moc_berryQtWidgetsTweaklet.cpp"
		},
		
		{
			"file" : "E:/D/MITK-superbuild/MITK-build/Plugins/org.blueberry.ui.qt/src/internal/moc_berryQtWidgetsTweakletImpl.cpp"
		},
		
		{
			"file" : "E:/D/MITK-superbuild/MITK-build/Plugins/org.blueberry.ui.qt/src/internal/moc_berryQtWorkbenchTweaklet.cpp"
		},
		
		{
			"file" : "E:/D/MITK-superbuild/MITK-build/Plugins/org.blueberry.ui.qt/src/internal/moc_berryQtWorkbenchPageTweaklet.cpp"
		},
		
		{
			"file" : "E:/D/MITK-superbuild/MITK-build/Plugins/org.blueberry.ui.qt/src/internal/moc_berryReopenEditorMenu.cpp"
		},
		
		{
			"file" : "E:/D/MITK-superbuild/MITK-build/Plugins/org.blueberry.ui.qt/src/internal/moc_berryShowViewMenu.cpp"
		},
		
		{
			"file" : "E:/D/MITK-superbuild/MITK-build/Plugins/org.blueberry.ui.qt/src/internal/moc_berrySwitchToWindowMenu.cpp"
		},
		
		{
			"file" : "E:/D/MITK-superbuild/MITK-build/Plugins/org.blueberry.ui.qt/src/internal/moc_berryWorkbenchPlugin.cpp"
		},
		
		{
			"file" : "E:/D/MITK-superbuild/MITK-build/Plugins/org.blueberry.ui.qt/src/internal/moc_berryWorkbenchSourceProvider.cpp"
		},
		
		{
			"file" : "E:/D/MITK-superbuild/MITK-build/Plugins/org.blueberry.ui.qt/src/internal/defaultpresentation/moc_berryNativeTabFolder.cpp"
		},
		
		{
			"file" : "E:/D/MITK-superbuild/MITK-build/Plugins/org.blueberry.ui.qt/src/internal/defaultpresentation/moc_berryNativeTabItem.cpp"
		},
		
		{
			"file" : "E:/D/MITK-superbuild/MITK-build/Plugins/org.blueberry.ui.qt/src/internal/defaultpresentation/moc_berryQCTabBar.cpp"
		},
		
		{
			"file" : "E:/D/MITK-superbuild/MITK-build/Plugins/org.blueberry.ui.qt/src/internal/defaultpresentation/moc_berryQtWorkbenchPresentationFactory.cpp"
		},
		
		{
			"file" : "E:/D/MITK-superbuild/MITK-build/Plugins/org.blueberry.ui.qt/src/internal/dialogs/moc_berryPerspectivesPreferencePage.cpp"
		},
		
		{
			"file" : "E:/D/MITK-superbuild/MITK-build/Plugins/org.blueberry.ui.qt/src/internal/dialogs/moc_berrySavePerspectiveDialog.cpp"
		},
		
		{
			"file" : "E:/D/MITK-superbuild/MITK-build/Plugins/org.blueberry.ui.qt/src/internal/handlers/moc_berryCloseAllPerspectivesHandler.cpp"
		},
		
		{
			"file" : "E:/D/MITK-superbuild/MITK-build/Plugins/org.blueberry.ui.qt/src/internal/handlers/moc_berryClosePerspectiveHandler.cpp"
		},
		
		{
			"file" : "E:/D/MITK-superbuild/MITK-build/Plugins/org.blueberry.ui.qt/src/internal/handlers/moc_berryDynamicHelpHandler.cpp"
		},
		
		{
			"file" : "E:/D/MITK-superbuild/MITK-build/Plugins/org.blueberry.ui.qt/src/internal/handlers/moc_berryHelpContentsHandler.cpp"
		},
		
		{
			"file" : "E:/D/MITK-superbuild/MITK-build/Plugins/org.blueberry.ui.qt/src/internal/handlers/moc_berryIntroHandler.cpp"
		},
		
		{
			"file" : "E:/D/MITK-superbuild/MITK-build/Plugins/org.blueberry.ui.qt/src/internal/handlers/moc_berryNewEditorHandler.cpp"
		},
		
		{
			"file" : "E:/D/MITK-superbuild/MITK-build/Plugins/org.blueberry.ui.qt/src/internal/handlers/moc_berryOpenInNewWindowHandler.cpp"
		},
		
		{
			"file" : "E:/D/MITK-superbuild/MITK-build/Plugins/org.blueberry.ui.qt/src/internal/handlers/moc_berryQuitHandler.cpp"
		},
		
		{
			"file" : "E:/D/MITK-superbuild/MITK-build/Plugins/org.blueberry.ui.qt/src/internal/handlers/moc_berryResetPerspectiveHandler.cpp"
		},
		
		{
			"file" : "E:/D/MITK-superbuild/MITK-build/Plugins/org.blueberry.ui.qt/src/internal/handlers/moc_berrySavePerspectiveHandler.cpp"
		},
		
		{
			"file" : "E:/D/MITK-superbuild/MITK-build/Plugins/org.blueberry.ui.qt/src/internal/handlers/moc_berryShowPerspectiveHandler.cpp"
		},
		
		{
			"file" : "E:/D/MITK-superbuild/MITK-build/Plugins/org.blueberry.ui.qt/src/internal/handlers/moc_berryShowViewHandler.cpp"
		},
		
		{
			"file" : "E:/D/MITK-superbuild/MITK-build/Plugins/org.blueberry.ui.qt/src/internal/intro/moc_berryEditorIntroAdapterPart.cpp"
		},
		
		{
			"file" : "E:/D/MITK-superbuild/MITK-build/Plugins/org.blueberry.ui.qt/ui_berryQtShowPerspectiveDialog.h"
		},
		
		{
			"file" : "E:/D/MITK-superbuild/MITK-build/Plugins/org.blueberry.ui.qt/ui_berryQtShowViewDialog.h"
		},
		
		{
			"file" : "E:/D/MITK-superbuild/MITK-build/Plugins/org.blueberry.ui.qt/ui_berryQtStylePreferencePage.h"
		},
		
		{
			"file" : "E:/D/MITK-superbuild/MITK-build/Plugins/org.blueberry.ui.qt/ui_berryQtStatusPart.h"
		},
		
		{
			"file" : "E:/D/MITK-superbuild/MITK-build/Plugins/org.blueberry.ui.qt/ui_berryPerspectivesPreferencePage.h"
		},
		
		{
			"file" : "E:/D/MITK-superbuild/MITK-build/Plugins/org.blueberry.ui.qt/ui_berrySavePerspectiveDialog.h"
		},
		
		{
			"file" : "E:/D/MITK-superbuild/MITK-build/Plugins/org.blueberry.ui.qt/qrc_org_blueberry_ui_qt.cpp"
		},
		
		{
			"file" : "E:/D/MITK-superbuild/MITK-build/Plugins/org.blueberry.ui.qt/qrc_org_blueberry_ui_qt_manifest.cpp"
		},
		
		{
			"file" : "E:/D/MITK-superbuild/MITK-build/Plugins/org.blueberry.ui.qt/qrc_org_blueberry_ui_qt_cached.cpp"
		},
		
		{
			"file" : "E:/D/MITK/Plugins/org.blueberry.ui.qt/CMakeLists.txt"
		},
		
		{
			"file" : "E:/D/MITK-superbuild/MITK-build/CMakeFiles/492ae6af5be180411fa6cb8e554a4ed6/moc_berryAbstractUICTKPlugin.cpp.rule"
		},
		
		{
			"file" : "E:/D/MITK-superbuild/MITK-build/CMakeFiles/492ae6af5be180411fa6cb8e554a4ed6/moc_berryEditorPart.cpp.rule"
		},
		
		{
			"file" : "E:/D/MITK-superbuild/MITK-build/CMakeFiles/492ae6af5be180411fa6cb8e554a4ed6/moc_berryExtensionFactory.cpp.rule"
		},
		
		{
			"file" : "E:/D/MITK-superbuild/MITK-build/CMakeFiles/492ae6af5be180411fa6cb8e554a4ed6/moc_berryQtSelectionProvider.cpp.rule"
		},
		
		{
			"file" : "E:/D/MITK-superbuild/MITK-build/CMakeFiles/492ae6af5be180411fa6cb8e554a4ed6/moc_berryViewPart.cpp.rule"
		},
		
		{
			"file" : "E:/D/MITK-superbuild/MITK-build/CMakeFiles/492ae6af5be180411fa6cb8e554a4ed6/moc_berryWorkbenchPart.cpp.rule"
		},
		
		{
			"file" : "E:/D/MITK-superbuild/MITK-build/CMakeFiles/e46c6a70b41c65695fcde020c315f951/moc_berryCommandContributionItem.cpp.rule"
		},
		
		{
			"file" : "E:/D/MITK-superbuild/MITK-build/CMakeFiles/e46c6a70b41c65695fcde020c315f951/moc_berryMenuManager.cpp.rule"
		},
		
		{
			"file" : "E:/D/MITK-superbuild/MITK-build/CMakeFiles/aabae9778ef535b0b55493a1f80d168d/moc_berryIntroPart.cpp.rule"
		},
		
		{
			"file" : "E:/D/MITK-superbuild/MITK-build/CMakeFiles/a6938d19ddb522b8927cec6c8a5ea50e/moc_berryPerspectiveListModel.cpp.rule"
		},
		
		{
			"file" : "E:/D/MITK-superbuild/MITK-build/CMakeFiles/a6938d19ddb522b8927cec6c8a5ea50e/moc_berryViewTreeModel.cpp.rule"
		},
		
		{
			"file" : "E:/D/MITK-superbuild/MITK-build/CMakeFiles/5448163a2d987b1fafb59808fc1ba4bd/moc_berryChangeToPerspectiveMenu.cpp.rule"
		},
		
		{
			"file" : "E:/D/MITK-superbuild/MITK-build/CMakeFiles/5448163a2d987b1fafb59808fc1ba4bd/moc_berryCommandServiceFactory.cpp.rule"
		},
		
		{
			"file" : "E:/D/MITK-superbuild/MITK-build/CMakeFiles/5448163a2d987b1fafb59808fc1ba4bd/moc_berryHandlerServiceFactory.cpp.rule"
		},
		
		{
			"file" : "E:/D/MITK-superbuild/MITK-build/CMakeFiles/5448163a2d987b1fafb59808fc1ba4bd/moc_berryMenuServiceFactory.cpp.rule"
		},
		
		{
			"file" : "E:/D/MITK-superbuild/MITK-build/CMakeFiles/5448163a2d987b1fafb59808fc1ba4bd/moc_berryOpenPerspectivePropertyTester.cpp.rule"
		},
		
		{
			"file" : "E:/D/MITK-superbuild/MITK-build/CMakeFiles/5448163a2d987b1fafb59808fc1ba4bd/moc_berryPerspectiveParameterValues.cpp.rule"
		},
		
		{
			"file" : "E:/D/MITK-superbuild/MITK-build/CMakeFiles/5448163a2d987b1fafb59808fc1ba4bd/moc_berryPreferencePageParameterValues.cpp.rule"
		},
		
		{
			"file" : "E:/D/MITK-superbuild/MITK-build/CMakeFiles/5448163a2d987b1fafb59808fc1ba4bd/moc_berryQtDisplay.cpp.rule"
		},
		
		{
			"file" : "E:/D/MITK-superbuild/MITK-build/CMakeFiles/5448163a2d987b1fafb59808fc1ba4bd/moc_berryQtGlobalEventFilter.cpp.rule"
		},
		
		{
			"file" : "E:/D/MITK-superbuild/MITK-build/CMakeFiles/5448163a2d987b1fafb59808fc1ba4bd/moc_berryQtMainWindowControl.cpp.rule"
		},
		
		{
			"file" : "E:/D/MITK-superbuild/MITK-build/CMakeFiles/5448163a2d987b1fafb59808fc1ba4bd/moc_berryQtOpenPerspectiveAction.cpp.rule"
		},
		
		{
			"file" : "E:/D/MITK-superbuild/MITK-build/CMakeFiles/5448163a2d987b1fafb59808fc1ba4bd/moc_berryQtPerspectiveSwitcher.cpp.rule"
		},
		
		{
			"file" : "E:/D/MITK-superbuild/MITK-build/CMakeFiles/5448163a2d987b1fafb59808fc1ba4bd/moc_berryQtSash.cpp.rule"
		},
		
		{
			"file" : "E:/D/MITK-superbuild/MITK-build/CMakeFiles/5448163a2d987b1fafb59808fc1ba4bd/moc_berryQtShowPerspectiveDialog.cpp.rule"
		},
		
		{
			"file" : "E:/D/MITK-superbuild/MITK-build/CMakeFiles/5448163a2d987b1fafb59808fc1ba4bd/moc_berryQtShowViewAction.cpp.rule"
		},
		
		{
			"file" : "E:/D/MITK-superbuild/MITK-build/CMakeFiles/5448163a2d987b1fafb59808fc1ba4bd/moc_berryQtShowViewDialog.cpp.rule"
		},
		
		{
			"file" : "E:/D/MITK-superbuild/MITK-build/CMakeFiles/5448163a2d987b1fafb59808fc1ba4bd/moc_berryQtStyleManager.cpp.rule"
		},
		
		{
			"file" : "E:/D/MITK-superbuild/MITK-build/CMakeFiles/5448163a2d987b1fafb59808fc1ba4bd/moc_berryQtStylePreferencePage.cpp.rule"
		},
		
		{
			"file" : "E:/D/MITK-superbuild/MITK-build/CMakeFiles/5448163a2d987b1fafb59808fc1ba4bd/moc_berryQtTracker.cpp.rule"
		},
		
		{
			"file" : "E:/D/MITK-superbuild/MITK-build/CMakeFiles/5448163a2d987b1fafb59808fc1ba4bd/moc_berryQtWidgetsTweaklet.cpp.rule"
		},
		
		{
			"file" : "E:/D/MITK-superbuild/MITK-build/CMakeFiles/5448163a2d987b1fafb59808fc1ba4bd/moc_berryQtWidgetsTweakletImpl.cpp.rule"
		},
		
		{
			"file" : "E:/D/MITK-superbuild/MITK-build/CMakeFiles/5448163a2d987b1fafb59808fc1ba4bd/moc_berryQtWorkbenchTweaklet.cpp.rule"
		},
		
		{
			"file" : "E:/D/MITK-superbuild/MITK-build/CMakeFiles/5448163a2d987b1fafb59808fc1ba4bd/moc_berryQtWorkbenchPageTweaklet.cpp.rule"
		},
		
		{
			"file" : "E:/D/MITK-superbuild/MITK-build/CMakeFiles/5448163a2d987b1fafb59808fc1ba4bd/moc_berryReopenEditorMenu.cpp.rule"
		},
		
		{
			"file" : "E:/D/MITK-superbuild/MITK-build/CMakeFiles/5448163a2d987b1fafb59808fc1ba4bd/moc_berryShowViewMenu.cpp.rule"
		},
		
		{
			"file" : "E:/D/MITK-superbuild/MITK-build/CMakeFiles/5448163a2d987b1fafb59808fc1ba4bd/moc_berrySwitchToWindowMenu.cpp.rule"
		},
		
		{
			"file" : "E:/D/MITK-superbuild/MITK-build/CMakeFiles/5448163a2d987b1fafb59808fc1ba4bd/moc_berryWorkbenchPlugin.cpp.rule"
		},
		
		{
			"file" : "E:/D/MITK-superbuild/MITK-build/CMakeFiles/5448163a2d987b1fafb59808fc1ba4bd/moc_berryWorkbenchSourceProvider.cpp.rule"
		},
		
		{
			"file" : "E:/D/MITK-superbuild/MITK-build/CMakeFiles/3ada9028ed9c8138bb2d770934944df1/moc_berryNativeTabFolder.cpp.rule"
		},
		
		{
			"file" : "E:/D/MITK-superbuild/MITK-build/CMakeFiles/3ada9028ed9c8138bb2d770934944df1/moc_berryNativeTabItem.cpp.rule"
		},
		
		{
			"file" : "E:/D/MITK-superbuild/MITK-build/CMakeFiles/3ada9028ed9c8138bb2d770934944df1/moc_berryQCTabBar.cpp.rule"
		},
		
		{
			"file" : "E:/D/MITK-superbuild/MITK-build/CMakeFiles/3ada9028ed9c8138bb2d770934944df1/moc_berryQtWorkbenchPresentationFactory.cpp.rule"
		},
		
		{
			"file" : "E:/D/MITK-superbuild/MITK-build/CMakeFiles/09922ddbc453fc8f490da249be1e2f04/moc_berryPerspectivesPreferencePage.cpp.rule"
		},
		
		{
			"file" : "E:/D/MITK-superbuild/MITK-build/CMakeFiles/09922ddbc453fc8f490da249be1e2f04/moc_berrySavePerspectiveDialog.cpp.rule"
		},
		
		{
			"file" : "E:/D/MITK-superbuild/MITK-build/CMakeFiles/a257dc240b66bdd43076d380ba102e8d/moc_berryCloseAllPerspectivesHandler.cpp.rule"
		},
		
		{
			"file" : "E:/D/MITK-superbuild/MITK-build/CMakeFiles/a257dc240b66bdd43076d380ba102e8d/moc_berryClosePerspectiveHandler.cpp.rule"
		},
		
		{
			"file" : "E:/D/MITK-superbuild/MITK-build/CMakeFiles/a257dc240b66bdd43076d380ba102e8d/moc_berryDynamicHelpHandler.cpp.rule"
		},
		
		{
			"file" : "E:/D/MITK-superbuild/MITK-build/CMakeFiles/a257dc240b66bdd43076d380ba102e8d/moc_berryHelpContentsHandler.cpp.rule"
		},
		
		{
			"file" : "E:/D/MITK-superbuild/MITK-build/CMakeFiles/a257dc240b66bdd43076d380ba102e8d/moc_berryIntroHandler.cpp.rule"
		},
		
		{
			"file" : "E:/D/MITK-superbuild/MITK-build/CMakeFiles/a257dc240b66bdd43076d380ba102e8d/moc_berryNewEditorHandler.cpp.rule"
		},
		
		{
			"file" : "E:/D/MITK-superbuild/MITK-build/CMakeFiles/a257dc240b66bdd43076d380ba102e8d/moc_berryOpenInNewWindowHandler.cpp.rule"
		},
		
		{
			"file" : "E:/D/MITK-superbuild/MITK-build/CMakeFiles/a257dc240b66bdd43076d380ba102e8d/moc_berryQuitHandler.cpp.rule"
		},
		
		{
			"file" : "E:/D/MITK-superbuild/MITK-build/CMakeFiles/a257dc240b66bdd43076d380ba102e8d/moc_berryResetPerspectiveHandler.cpp.rule"
		},
		
		{
			"file" : "E:/D/MITK-superbuild/MITK-build/CMakeFiles/a257dc240b66bdd43076d380ba102e8d/moc_berrySavePerspectiveHandler.cpp.rule"
		},
		
		{
			"file" : "E:/D/MITK-superbuild/MITK-build/CMakeFiles/a257dc240b66bdd43076d380ba102e8d/moc_berryShowPerspectiveHandler.cpp.rule"
		},
		
		{
			"file" : "E:/D/MITK-superbuild/MITK-build/CMakeFiles/a257dc240b66bdd43076d380ba102e8d/moc_berryShowViewHandler.cpp.rule"
		},
		
		{
			"file" : "E:/D/MITK-superbuild/MITK-build/CMakeFiles/1cfb1ff3e4b938dcf745ff817fdbe1b4/moc_berryEditorIntroAdapterPart.cpp.rule"
		},
		
		{
			"file" : "E:/D/MITK/Plugins/org.blueberry.ui.qt/src/internal/berryQtShowPerspectiveDialog.ui"
		},
		
		{
			"file" : "E:/D/MITK/Plugins/org.blueberry.ui.qt/src/internal/berryQtShowViewDialog.ui"
		},
		
		{
			"file" : "E:/D/MITK/Plugins/org.blueberry.ui.qt/src/internal/berryQtStylePreferencePage.ui"
		},
		
		{
			"file" : "E:/D/MITK/Plugins/org.blueberry.ui.qt/src/internal/berryQtStatusPart.ui"
		},
		
		{
			"file" : "E:/D/MITK/Plugins/org.blueberry.ui.qt/src/internal/dialogs/berryPerspectivesPreferencePage.ui"
		},
		
		{
			"file" : "E:/D/MITK/Plugins/org.blueberry.ui.qt/src/internal/dialogs/berrySavePerspectiveDialog.ui"
		},
		
		{
			"file" : "E:/D/MITK/Plugins/org.blueberry.ui.qt/resources/org_blueberry_ui_qt.qrc"
		},
		
		{
			"file" : "E:/D/MITK-superbuild/MITK-build/Plugins/org.blueberry.ui.qt/org_blueberry_ui_qt_manifest.qrc"
		},
		
		{
			"file" : "E:/D/MITK-superbuild/MITK-build/Plugins/org.blueberry.ui.qt/org_blueberry_ui_qt_cached.qrc"
		}
	],
	"target" : 
	{
		"labels" : [ "MITK-Plugins" ],
		"name" : "org_blueberry_ui_qt"
	}
}
